{"subjectDetails":{"gender":"male","age":"16","fstLan":"Swedish","javaExp":"None","reactExp":"Hobby level with moderate understanding","comments":"","origin":" 6"},"snippetOrder":[],"snippetsLeft":["1I","4R","6S","14I","5R","3S","9I","12R","12S","13I","6R","11S","8I","13R","7S","5I","8R","5S","11I","14R","13S","15I","3R","10S","4I","10R","4S","3I","1R","2S","6I","15R","14S","2I","11R","1S","7I","7R","8S","12I","9R","9S","10I","2R","15S"],"calibrations":[{"readings":[{"gazeData":[{"timeStamp":100861.00000000003,"x":439,"y":368},{"timeStamp":100920,"x":439,"y":368},{"timeStamp":100952,"x":439,"y":368},{"timeStamp":100978,"x":439,"y":368},{"timeStamp":101000,"x":439,"y":368},{"timeStamp":101024,"x":439,"y":368},{"timeStamp":101047,"x":439,"y":368},{"timeStamp":101065,"x":439,"y":368},{"timeStamp":101084,"x":439,"y":368},{"timeStamp":101102,"x":439,"y":368},{"timeStamp":101122,"x":439,"y":368},{"timeStamp":101141.00000000003,"x":439,"y":368},{"timeStamp":101160,"x":439,"y":368},{"timeStamp":101178,"x":439,"y":368},{"timeStamp":101195,"x":439,"y":368},{"timeStamp":101211,"x":439,"y":368},{"timeStamp":101227,"x":439,"y":368},{"timeStamp":101244,"x":439,"y":368},{"timeStamp":101264,"x":439,"y":368},{"timeStamp":101284.00000000003,"x":439,"y":368},{"timeStamp":101301,"x":439,"y":368},{"timeStamp":101319,"x":439,"y":368},{"timeStamp":101336,"x":439,"y":368},{"timeStamp":101355.00000000003,"x":439,"y":368},{"timeStamp":101371,"x":439,"y":368},{"timeStamp":101390,"x":439,"y":368},{"timeStamp":101410,"x":439,"y":368},{"timeStamp":101428,"x":439,"y":368},{"timeStamp":101446,"x":439,"y":368},{"timeStamp":101462,"x":439,"y":368},{"timeStamp":101477,"x":439,"y":368},{"timeStamp":101494,"x":439,"y":368},{"timeStamp":101509,"x":439,"y":368},{"timeStamp":101525,"x":439,"y":368},{"timeStamp":101541,"x":439,"y":368},{"timeStamp":101567,"x":439,"y":368},{"timeStamp":101584,"x":439,"y":368},{"timeStamp":101600,"x":439,"y":368},{"timeStamp":101616,"x":439,"y":368},{"timeStamp":101631,"x":439,"y":368},{"timeStamp":101646,"x":439,"y":368},{"timeStamp":101677.00000000003,"x":439,"y":368},{"timeStamp":101694,"x":439,"y":368},{"timeStamp":101714,"x":439,"y":368},{"timeStamp":101730.00000000003,"x":439,"y":368},{"timeStamp":101747,"x":439,"y":368},{"timeStamp":101764,"x":439,"y":368},{"timeStamp":101784.00000000003,"x":439,"y":368},{"timeStamp":101802.00000000003,"x":439,"y":368},{"timeStamp":101822,"x":439,"y":368},{"timeStamp":101842,"x":439,"y":368},{"timeStamp":101860,"x":439,"y":368},{"timeStamp":101878,"x":439,"y":368},{"timeStamp":101896,"x":439,"y":368},{"timeStamp":101915.00000000003,"x":439,"y":368},{"timeStamp":101931,"x":439,"y":368},{"timeStamp":101949,"x":439,"y":368},{"timeStamp":101965,"x":439,"y":368},{"timeStamp":101987,"x":439,"y":368},{"timeStamp":102004.00000000003,"x":439,"y":368},{"timeStamp":102024,"x":439,"y":368},{"timeStamp":102041,"x":439,"y":368},{"timeStamp":102058.00000000003,"x":439,"y":368},{"timeStamp":102076,"x":439,"y":368},{"timeStamp":102094,"x":439,"y":368},{"timeStamp":102114,"x":439,"y":368},{"timeStamp":102135.00000000003,"x":439,"y":368},{"timeStamp":102154,"x":439,"y":368},{"timeStamp":102170,"x":439,"y":368},{"timeStamp":102187,"x":439,"y":368}],"xPos":710.83,"yPos":30,"pointNumber":26},{"gazeData":[{"timeStamp":103709,"x":439,"y":368},{"timeStamp":103770,"x":439,"y":368},{"timeStamp":103799,"x":439,"y":368},{"timeStamp":103825,"x":439,"y":368},{"timeStamp":103847,"x":439,"y":368},{"timeStamp":103868,"x":439,"y":368},{"timeStamp":103886,"x":439,"y":368},{"timeStamp":103905,"x":439,"y":368},{"timeStamp":103924,"x":439,"y":368},{"timeStamp":103943,"x":439,"y":368},{"timeStamp":103960,"x":439,"y":368},{"timeStamp":103979,"x":439,"y":368},{"timeStamp":103996,"x":439,"y":368},{"timeStamp":104016.00000000003,"x":439,"y":368},{"timeStamp":104034.00000000003,"x":439,"y":368},{"timeStamp":104054,"x":439,"y":368},{"timeStamp":104071,"x":439,"y":368},{"timeStamp":104091,"x":439,"y":368},{"timeStamp":104111.00000000003,"x":439,"y":368},{"timeStamp":104128,"x":439,"y":368},{"timeStamp":104146,"x":439,"y":368},{"timeStamp":104163,"x":439,"y":368},{"timeStamp":104180,"x":439,"y":368},{"timeStamp":104198,"x":439,"y":368},{"timeStamp":104217,"x":439,"y":368},{"timeStamp":104234,"x":439,"y":368},{"timeStamp":104253,"x":439,"y":368},{"timeStamp":104272.00000000003,"x":439,"y":368},{"timeStamp":104290.00000000003,"x":439,"y":368},{"timeStamp":104310,"x":439,"y":368},{"timeStamp":104328,"x":439,"y":368},{"timeStamp":104347,"x":439,"y":368},{"timeStamp":104367.00000000003,"x":439,"y":368},{"timeStamp":104387,"x":439,"y":368},{"timeStamp":104404,"x":439,"y":368},{"timeStamp":104424,"x":439,"y":368},{"timeStamp":104441,"x":439,"y":368},{"timeStamp":104458,"x":439,"y":368},{"timeStamp":104477,"x":439,"y":368},{"timeStamp":104493,"x":439,"y":368},{"timeStamp":104511,"x":439,"y":368},{"timeStamp":104531,"x":439,"y":368},{"timeStamp":104550,"x":439,"y":368},{"timeStamp":104568,"x":439,"y":368},{"timeStamp":104591,"x":439,"y":368},{"timeStamp":104609,"x":439,"y":368},{"timeStamp":104628,"x":439,"y":368},{"timeStamp":104644,"x":439,"y":368},{"timeStamp":104661,"x":439,"y":368},{"timeStamp":104681,"x":439,"y":368},{"timeStamp":104699,"x":439,"y":368},{"timeStamp":104718,"x":439,"y":368},{"timeStamp":104735,"x":439,"y":368},{"timeStamp":104754.00000000003,"x":439,"y":368},{"timeStamp":104771,"x":439,"y":368},{"timeStamp":104790.00000000003,"x":439,"y":368},{"timeStamp":104817,"x":439,"y":368},{"timeStamp":104834,"x":439,"y":368},{"timeStamp":104853,"x":439,"y":368},{"timeStamp":104872,"x":439,"y":368},{"timeStamp":104891.00000000003,"x":439,"y":368},{"timeStamp":104908,"x":439,"y":368},{"timeStamp":104927.00000000003,"x":439,"y":368},{"timeStamp":104944,"x":439,"y":368},{"timeStamp":104960,"x":439,"y":368},{"timeStamp":104978,"x":439,"y":368},{"timeStamp":104995,"x":439,"y":368},{"timeStamp":105014,"x":439,"y":368}],"xPos":166.17,"yPos":370,"pointNumber":27},{"gazeData":[{"timeStamp":106537,"x":439,"y":368},{"timeStamp":106603,"x":439,"y":368},{"timeStamp":106633,"x":439,"y":368},{"timeStamp":106659.00000000003,"x":439,"y":368},{"timeStamp":106679,"x":439,"y":368},{"timeStamp":106703,"x":439,"y":368},{"timeStamp":106727,"x":439,"y":368},{"timeStamp":106744,"x":439,"y":368},{"timeStamp":106761,"x":439,"y":368},{"timeStamp":106783,"x":439,"y":368},{"timeStamp":106800,"x":439,"y":368},{"timeStamp":106820,"x":439,"y":368},{"timeStamp":106837,"x":439,"y":368},{"timeStamp":106856,"x":439,"y":368},{"timeStamp":106872,"x":439,"y":368},{"timeStamp":106889,"x":439,"y":368},{"timeStamp":106908,"x":439,"y":368},{"timeStamp":106928,"x":439,"y":368},{"timeStamp":106948,"x":439,"y":368},{"timeStamp":106965,"x":439,"y":368},{"timeStamp":106984,"x":439,"y":368},{"timeStamp":107001,"x":439,"y":368},{"timeStamp":107021,"x":439,"y":368},{"timeStamp":107040.00000000003,"x":439,"y":368},{"timeStamp":107058.00000000003,"x":439,"y":368},{"timeStamp":107077,"x":439,"y":368},{"timeStamp":107097,"x":439,"y":368},{"timeStamp":107116,"x":439,"y":368},{"timeStamp":107133,"x":439,"y":368},{"timeStamp":107150,"x":439,"y":368},{"timeStamp":107166,"x":439,"y":368},{"timeStamp":107185,"x":439,"y":368},{"timeStamp":107204,"x":439,"y":368},{"timeStamp":107224.00000000003,"x":439,"y":368},{"timeStamp":107247,"x":439,"y":368},{"timeStamp":107265,"x":439,"y":368},{"timeStamp":107283,"x":439,"y":368},{"timeStamp":107300,"x":439,"y":368},{"timeStamp":107319,"x":439,"y":368},{"timeStamp":107338,"x":439,"y":368},{"timeStamp":107356,"x":439,"y":368},{"timeStamp":107375,"x":439,"y":368},{"timeStamp":107392,"x":439,"y":368},{"timeStamp":107411,"x":439,"y":368},{"timeStamp":107428,"x":439,"y":368},{"timeStamp":107448,"x":439,"y":368},{"timeStamp":107464,"x":439,"y":368},{"timeStamp":107481,"x":439,"y":368},{"timeStamp":107498.00000000003,"x":439,"y":368},{"timeStamp":107516.00000000003,"x":439,"y":368},{"timeStamp":107534.00000000003,"x":439,"y":368},{"timeStamp":107553,"x":439,"y":368},{"timeStamp":107570,"x":439,"y":368},{"timeStamp":107588,"x":439,"y":368},{"timeStamp":107607,"x":439,"y":368},{"timeStamp":107624,"x":439,"y":368},{"timeStamp":107642,"x":439,"y":368},{"timeStamp":107660,"x":439,"y":368},{"timeStamp":107679,"x":439,"y":368},{"timeStamp":107695,"x":439,"y":368},{"timeStamp":107713,"x":439,"y":368},{"timeStamp":107730.00000000003,"x":439,"y":368},{"timeStamp":107750,"x":439,"y":368},{"timeStamp":107765,"x":439,"y":368},{"timeStamp":107781,"x":439,"y":368},{"timeStamp":107797,"x":439,"y":368},{"timeStamp":107813,"x":439,"y":368},{"timeStamp":107832,"x":439,"y":368}],"xPos":438.5,"yPos":370,"pointNumber":28},{"gazeData":[{"timeStamp":109358,"x":439,"y":368},{"timeStamp":109420,"x":439,"y":368},{"timeStamp":109449,"x":439,"y":368},{"timeStamp":109475,"x":439,"y":368},{"timeStamp":109500,"x":439,"y":368},{"timeStamp":109525,"x":439,"y":368},{"timeStamp":109551,"x":439,"y":368},{"timeStamp":109568,"x":439,"y":368},{"timeStamp":109585,"x":439,"y":368},{"timeStamp":109603,"x":439,"y":368},{"timeStamp":109620,"x":439,"y":368},{"timeStamp":109639,"x":439,"y":368},{"timeStamp":109657,"x":439,"y":368},{"timeStamp":109673,"x":439,"y":368},{"timeStamp":109689,"x":439,"y":368},{"timeStamp":109705,"x":439,"y":368},{"timeStamp":109723,"x":439,"y":368},{"timeStamp":109741,"x":439,"y":368},{"timeStamp":109757,"x":439,"y":368},{"timeStamp":109776,"x":439,"y":368},{"timeStamp":109792,"x":439,"y":368},{"timeStamp":109808.00000000003,"x":439,"y":368},{"timeStamp":109824,"x":439,"y":368},{"timeStamp":109841,"x":439,"y":368},{"timeStamp":109860,"x":439,"y":368},{"timeStamp":109877,"x":439,"y":368},{"timeStamp":109894,"x":439,"y":368},{"timeStamp":109913,"x":439,"y":368},{"timeStamp":109930,"x":439,"y":368},{"timeStamp":109950,"x":439,"y":368},{"timeStamp":109968,"x":439,"y":368},{"timeStamp":109986.00000000003,"x":439,"y":368},{"timeStamp":110003,"x":439,"y":368},{"timeStamp":110024,"x":439,"y":368},{"timeStamp":110044,"x":439,"y":368},{"timeStamp":110061,"x":439,"y":368},{"timeStamp":110080,"x":439,"y":368},{"timeStamp":110098,"x":439,"y":368},{"timeStamp":110117.00000000003,"x":439,"y":368},{"timeStamp":110134,"x":439,"y":368},{"timeStamp":110154,"x":439,"y":368},{"timeStamp":110174,"x":439,"y":368},{"timeStamp":110193,"x":439,"y":368},{"timeStamp":110212,"x":439,"y":368},{"timeStamp":110229,"x":439,"y":368},{"timeStamp":110249,"x":439,"y":368},{"timeStamp":110266.00000000003,"x":439,"y":368},{"timeStamp":110285,"x":439,"y":368},{"timeStamp":110307,"x":439,"y":368},{"timeStamp":110325,"x":439,"y":368},{"timeStamp":110341,"x":439,"y":368},{"timeStamp":110358,"x":439,"y":368},{"timeStamp":110374,"x":439,"y":368},{"timeStamp":110390,"x":439,"y":368},{"timeStamp":110406,"x":439,"y":368},{"timeStamp":110422,"x":439,"y":368},{"timeStamp":110437,"x":439,"y":368},{"timeStamp":110456,"x":439,"y":368},{"timeStamp":110472,"x":439,"y":368},{"timeStamp":110488,"x":439,"y":368},{"timeStamp":110503,"x":439,"y":368},{"timeStamp":110520,"x":439,"y":368},{"timeStamp":110536,"x":439,"y":368},{"timeStamp":110555,"x":439,"y":368},{"timeStamp":110574,"x":439,"y":368},{"timeStamp":110591,"x":439,"y":368},{"timeStamp":110608,"x":439,"y":368}],"xPos":166.17,"yPos":710,"pointNumber":29},{"gazeData":[{"timeStamp":112131,"x":439,"y":368},{"timeStamp":112186,"x":439,"y":368},{"timeStamp":112216,"x":439,"y":368},{"timeStamp":112242.00000000003,"x":439,"y":368},{"timeStamp":112266.00000000003,"x":439,"y":368},{"timeStamp":112293,"x":439,"y":368},{"timeStamp":112318,"x":439,"y":368},{"timeStamp":112338,"x":439,"y":368},{"timeStamp":112356,"x":439,"y":368},{"timeStamp":112373.00000000003,"x":439,"y":368},{"timeStamp":112391.00000000003,"x":439,"y":368},{"timeStamp":112407,"x":439,"y":368},{"timeStamp":112425,"x":439,"y":368},{"timeStamp":112445,"x":439,"y":368},{"timeStamp":112464,"x":439,"y":368},{"timeStamp":112488,"x":439,"y":368},{"timeStamp":112508,"x":439,"y":368},{"timeStamp":112524,"x":439,"y":368},{"timeStamp":112545,"x":439,"y":368},{"timeStamp":112563,"x":439,"y":368},{"timeStamp":112582,"x":439,"y":368},{"timeStamp":112597,"x":439,"y":368},{"timeStamp":112613,"x":439,"y":368},{"timeStamp":112629.00000000003,"x":439,"y":368},{"timeStamp":112645,"x":439,"y":368},{"timeStamp":112662,"x":439,"y":368},{"timeStamp":112678,"x":439,"y":368},{"timeStamp":112697,"x":439,"y":368},{"timeStamp":112715,"x":439,"y":368},{"timeStamp":112732,"x":439,"y":368},{"timeStamp":112751,"x":439,"y":368},{"timeStamp":112770,"x":439,"y":368},{"timeStamp":112787,"x":439,"y":368},{"timeStamp":112806,"x":439,"y":368},{"timeStamp":112826,"x":439,"y":368},{"timeStamp":112846,"x":439,"y":368},{"timeStamp":112863,"x":439,"y":368},{"timeStamp":112883,"x":439,"y":368},{"timeStamp":112900,"x":439,"y":368},{"timeStamp":112920,"x":439,"y":368},{"timeStamp":112938,"x":439,"y":368},{"timeStamp":112956,"x":439,"y":368},{"timeStamp":112975,"x":439,"y":368},{"timeStamp":112995,"x":439,"y":368},{"timeStamp":113014,"x":439,"y":368},{"timeStamp":113032,"x":439,"y":368},{"timeStamp":113051,"x":439,"y":368},{"timeStamp":113069,"x":439,"y":368},{"timeStamp":113088,"x":439,"y":368},{"timeStamp":113107,"x":439,"y":368},{"timeStamp":113127,"x":439,"y":368},{"timeStamp":113144,"x":439,"y":368},{"timeStamp":113160,"x":439,"y":368},{"timeStamp":113178,"x":439,"y":368},{"timeStamp":113196,"x":439,"y":368},{"timeStamp":113214,"x":439,"y":368},{"timeStamp":113232,"x":439,"y":368},{"timeStamp":113251,"x":439,"y":368},{"timeStamp":113270,"x":439,"y":368},{"timeStamp":113290.00000000003,"x":439,"y":368},{"timeStamp":113307,"x":439,"y":368},{"timeStamp":113323,"x":439,"y":368},{"timeStamp":113340,"x":439,"y":368},{"timeStamp":113357,"x":439,"y":368},{"timeStamp":113377,"x":439,"y":368},{"timeStamp":113395,"x":439,"y":368},{"timeStamp":113418,"x":439,"y":368},{"timeStamp":113435,"x":439,"y":368},{"timeStamp":113454,"x":439,"y":368},{"timeStamp":113473,"x":439,"y":368},{"timeStamp":113490,"x":439,"y":368},{"timeStamp":113508,"x":439,"y":368}],"xPos":710.83,"yPos":710,"pointNumber":30},{"gazeData":[{"timeStamp":115031,"x":439,"y":368},{"timeStamp":115086,"x":439,"y":368},{"timeStamp":115116,"x":439,"y":368},{"timeStamp":115143,"x":439,"y":368},{"timeStamp":115166,"x":439,"y":368},{"timeStamp":115189.00000000003,"x":439,"y":368},{"timeStamp":115213,"x":439,"y":368},{"timeStamp":115232,"x":439,"y":368},{"timeStamp":115250,"x":439,"y":368},{"timeStamp":115268,"x":439,"y":368},{"timeStamp":115287,"x":439,"y":368},{"timeStamp":115306,"x":439,"y":368},{"timeStamp":115328,"x":439,"y":368},{"timeStamp":115347,"x":439,"y":368},{"timeStamp":115365,"x":439,"y":368},{"timeStamp":115385.00000000003,"x":439,"y":368},{"timeStamp":115404,"x":439,"y":368},{"timeStamp":115422,"x":439,"y":368},{"timeStamp":115441,"x":439,"y":368},{"timeStamp":115457,"x":439,"y":368},{"timeStamp":115477,"x":439,"y":368},{"timeStamp":115496,"x":439,"y":368},{"timeStamp":115515,"x":439,"y":368},{"timeStamp":115533,"x":439,"y":368},{"timeStamp":115552.00000000003,"x":439,"y":368},{"timeStamp":115571,"x":439,"y":368},{"timeStamp":115588,"x":439,"y":368},{"timeStamp":115606,"x":439,"y":368},{"timeStamp":115623.00000000003,"x":439,"y":368},{"timeStamp":115640,"x":439,"y":368},{"timeStamp":115659.00000000003,"x":439,"y":368},{"timeStamp":115679,"x":439,"y":368},{"timeStamp":115696,"x":439,"y":368},{"timeStamp":115713,"x":439,"y":368},{"timeStamp":115730.00000000003,"x":439,"y":368},{"timeStamp":115749,"x":439,"y":368},{"timeStamp":115768,"x":439,"y":368},{"timeStamp":115787,"x":439,"y":368},{"timeStamp":115806,"x":439,"y":368},{"timeStamp":115823,"x":439,"y":368},{"timeStamp":115843,"x":439,"y":368},{"timeStamp":115859,"x":439,"y":368},{"timeStamp":115876,"x":439,"y":368},{"timeStamp":115895,"x":439,"y":368},{"timeStamp":115912,"x":439,"y":368},{"timeStamp":115929,"x":439,"y":368},{"timeStamp":115951,"x":439,"y":368},{"timeStamp":115969,"x":439,"y":368},{"timeStamp":115988,"x":439,"y":368},{"timeStamp":116007,"x":439,"y":368},{"timeStamp":116024,"x":439,"y":368},{"timeStamp":116042,"x":439,"y":368},{"timeStamp":116059,"x":439,"y":368},{"timeStamp":116078,"x":439,"y":368},{"timeStamp":116095,"x":439,"y":368},{"timeStamp":116115,"x":439,"y":368},{"timeStamp":116135.00000000003,"x":439,"y":368},{"timeStamp":116153.00000000003,"x":439,"y":368},{"timeStamp":116169,"x":439,"y":368},{"timeStamp":116187,"x":439,"y":368},{"timeStamp":116206,"x":439,"y":368},{"timeStamp":116223,"x":439,"y":368},{"timeStamp":116245,"x":439,"y":368},{"timeStamp":116263,"x":439,"y":368},{"timeStamp":116282,"x":439,"y":368},{"timeStamp":116298,"x":439,"y":368},{"timeStamp":116315,"x":439,"y":368},{"timeStamp":116334,"x":439,"y":368}],"xPos":166.17,"yPos":30,"pointNumber":31},{"gazeData":[{"timeStamp":117859,"x":439,"y":368},{"timeStamp":117920,"x":439,"y":368},{"timeStamp":117949,"x":439,"y":368},{"timeStamp":117977,"x":439,"y":368},{"timeStamp":117998.00000000003,"x":439,"y":368},{"timeStamp":118023,"x":439,"y":368},{"timeStamp":118049,"x":439,"y":368},{"timeStamp":118069,"x":439,"y":368},{"timeStamp":118087,"x":439,"y":368},{"timeStamp":118106,"x":439,"y":368},{"timeStamp":118123.00000000003,"x":439,"y":368},{"timeStamp":118141.00000000003,"x":439,"y":368},{"timeStamp":118160,"x":439,"y":368},{"timeStamp":118180,"x":439,"y":368},{"timeStamp":118197,"x":439,"y":368},{"timeStamp":118217,"x":439,"y":368},{"timeStamp":118236.00000000003,"x":439,"y":368},{"timeStamp":118254.00000000003,"x":439,"y":368},{"timeStamp":118274,"x":439,"y":368},{"timeStamp":118291,"x":439,"y":368},{"timeStamp":118309,"x":439,"y":368},{"timeStamp":118327,"x":439,"y":368},{"timeStamp":118348,"x":439,"y":368},{"timeStamp":118366,"x":439,"y":368},{"timeStamp":118385.00000000003,"x":439,"y":368},{"timeStamp":118402,"x":439,"y":368},{"timeStamp":118419,"x":439,"y":368},{"timeStamp":118435,"x":439,"y":368},{"timeStamp":118453,"x":439,"y":368},{"timeStamp":118472,"x":439,"y":368},{"timeStamp":118489,"x":439,"y":368},{"timeStamp":118507,"x":439,"y":368},{"timeStamp":118524,"x":439,"y":368},{"timeStamp":118543,"x":439,"y":368},{"timeStamp":118560,"x":439,"y":368},{"timeStamp":118578,"x":439,"y":368},{"timeStamp":118595,"x":439,"y":368},{"timeStamp":118615,"x":439,"y":368},{"timeStamp":118634,"x":439,"y":368},{"timeStamp":118653.00000000003,"x":439,"y":368},{"timeStamp":118674,"x":439,"y":368},{"timeStamp":118692,"x":439,"y":368},{"timeStamp":118711,"x":439,"y":368},{"timeStamp":118728,"x":439,"y":368},{"timeStamp":118748.00000000003,"x":439,"y":368},{"timeStamp":118764,"x":439,"y":368},{"timeStamp":118786,"x":439,"y":368},{"timeStamp":118804,"x":439,"y":368},{"timeStamp":118821,"x":439,"y":368},{"timeStamp":118839,"x":439,"y":368},{"timeStamp":118855.00000000003,"x":439,"y":368},{"timeStamp":118870,"x":439,"y":368},{"timeStamp":118886,"x":439,"y":368},{"timeStamp":118906,"x":439,"y":368},{"timeStamp":118923,"x":439,"y":368},{"timeStamp":118942,"x":439,"y":368},{"timeStamp":118959,"x":439,"y":368},{"timeStamp":118977,"x":439,"y":368},{"timeStamp":118994,"x":439,"y":368},{"timeStamp":119011,"x":439,"y":368},{"timeStamp":119027,"x":439,"y":368},{"timeStamp":119045,"x":439,"y":368},{"timeStamp":119061,"x":439,"y":368},{"timeStamp":119080,"x":439,"y":368},{"timeStamp":119097,"x":439,"y":368},{"timeStamp":119113,"x":439,"y":368},{"timeStamp":119129.00000000003,"x":439,"y":368}],"xPos":710.83,"yPos":370,"pointNumber":32}],"dimensions":{"x":0,"y":0,"h":740,"w":877},"time":"2021-09-10 20:36:03"},{"readings":[{"gazeData":[{"timeStamp":212038,"x":208,"y":343},{"timeStamp":212121,"x":535,"y":380},{"timeStamp":212146,"x":208,"y":343},{"timeStamp":212172,"x":535,"y":380},{"timeStamp":212203,"x":208,"y":343},{"timeStamp":212221,"x":535,"y":380},{"timeStamp":212243,"x":208,"y":343},{"timeStamp":212263.00000000006,"x":535,"y":380},{"timeStamp":212282,"x":208,"y":343},{"timeStamp":212301,"x":535,"y":380},{"timeStamp":212321,"x":208,"y":343},{"timeStamp":212340,"x":535,"y":380},{"timeStamp":212358,"x":208,"y":343},{"timeStamp":212377,"x":535,"y":380},{"timeStamp":212394,"x":208,"y":343},{"timeStamp":212413,"x":535,"y":380},{"timeStamp":212433,"x":208,"y":343},{"timeStamp":212451,"x":535,"y":380},{"timeStamp":212468,"x":208,"y":343},{"timeStamp":212485,"x":535,"y":380},{"timeStamp":212504,"x":208,"y":343},{"timeStamp":212521,"x":535,"y":380},{"timeStamp":212540,"x":208,"y":343},{"timeStamp":212557,"x":535,"y":380},{"timeStamp":212576,"x":208,"y":343},{"timeStamp":212596,"x":535,"y":380},{"timeStamp":212616,"x":208,"y":343},{"timeStamp":212632,"x":535,"y":380},{"timeStamp":212651,"x":208,"y":343},{"timeStamp":212669,"x":535,"y":380},{"timeStamp":212687,"x":208,"y":343},{"timeStamp":212706,"x":535,"y":380},{"timeStamp":212724,"x":208,"y":343},{"timeStamp":212743,"x":535,"y":380},{"timeStamp":212761,"x":208,"y":343},{"timeStamp":212780,"x":535,"y":380},{"timeStamp":212797,"x":208,"y":343},{"timeStamp":212815,"x":535,"y":380},{"timeStamp":212832,"x":208,"y":343},{"timeStamp":212848,"x":535,"y":380},{"timeStamp":212866,"x":208,"y":343},{"timeStamp":212883,"x":535,"y":380},{"timeStamp":212903,"x":208,"y":343},{"timeStamp":212920,"x":535,"y":380},{"timeStamp":212939,"x":208,"y":343},{"timeStamp":212955,"x":535,"y":380},{"timeStamp":212976,"x":208,"y":343},{"timeStamp":212992,"x":535,"y":380},{"timeStamp":213009,"x":208,"y":343},{"timeStamp":213027,"x":535,"y":380},{"timeStamp":213049.00000000006,"x":208,"y":343},{"timeStamp":213068,"x":535,"y":380},{"timeStamp":213084,"x":208,"y":343},{"timeStamp":213101,"x":535,"y":380},{"timeStamp":213118,"x":208,"y":343},{"timeStamp":213137,"x":535,"y":380},{"timeStamp":213154,"x":208,"y":343},{"timeStamp":213176,"x":535,"y":380},{"timeStamp":213193,"x":208,"y":343},{"timeStamp":213213,"x":535,"y":380},{"timeStamp":213232,"x":208,"y":343},{"timeStamp":213249,"x":535,"y":380},{"timeStamp":213270,"x":208,"y":343},{"timeStamp":213288,"x":535,"y":380},{"timeStamp":213307,"x":208,"y":343},{"timeStamp":213323.00000000006,"x":535,"y":380}],"xPos":166.17,"yPos":710,"pointNumber":26},{"gazeData":[{"timeStamp":214845,"x":208,"y":343},{"timeStamp":214904,"x":535,"y":380},{"timeStamp":214936.00000000006,"x":208,"y":343},{"timeStamp":214961,"x":535,"y":380},{"timeStamp":214986,"x":208,"y":343},{"timeStamp":215011,"x":535,"y":380},{"timeStamp":215038,"x":208,"y":343},{"timeStamp":215056,"x":535,"y":380},{"timeStamp":215072,"x":208,"y":343},{"timeStamp":215087,"x":535,"y":380},{"timeStamp":215107,"x":208,"y":343},{"timeStamp":215123,"x":535,"y":380},{"timeStamp":215142,"x":208,"y":343},{"timeStamp":215159,"x":535,"y":380},{"timeStamp":215174.00000000006,"x":208,"y":343},{"timeStamp":215189,"x":535,"y":380},{"timeStamp":215205,"x":208,"y":343},{"timeStamp":215224,"x":535,"y":380},{"timeStamp":215241,"x":208,"y":343},{"timeStamp":215258,"x":535,"y":380},{"timeStamp":215276,"x":208,"y":343},{"timeStamp":215295,"x":535,"y":380},{"timeStamp":215314,"x":208,"y":343},{"timeStamp":215331,"x":535,"y":380},{"timeStamp":215347.00000000006,"x":208,"y":343},{"timeStamp":215367,"x":535,"y":380},{"timeStamp":215386,"x":208,"y":343},{"timeStamp":215405,"x":535,"y":380},{"timeStamp":215422,"x":208,"y":343},{"timeStamp":215441,"x":535,"y":380},{"timeStamp":215457,"x":208,"y":343},{"timeStamp":215478,"x":535,"y":380},{"timeStamp":215494,"x":208,"y":343},{"timeStamp":215511,"x":535,"y":380},{"timeStamp":215528,"x":208,"y":343},{"timeStamp":215548,"x":535,"y":380},{"timeStamp":215565,"x":208,"y":343},{"timeStamp":215581,"x":535,"y":380},{"timeStamp":215598,"x":208,"y":343},{"timeStamp":215614.00000000006,"x":535,"y":380},{"timeStamp":215631,"x":208,"y":343},{"timeStamp":215649,"x":535,"y":380},{"timeStamp":215669,"x":208,"y":343},{"timeStamp":215689,"x":535,"y":380},{"timeStamp":215707,"x":208,"y":343},{"timeStamp":215723,"x":535,"y":380},{"timeStamp":215740,"x":208,"y":343},{"timeStamp":215757,"x":535,"y":380},{"timeStamp":215777,"x":208,"y":343},{"timeStamp":215795,"x":535,"y":380},{"timeStamp":215814,"x":208,"y":343},{"timeStamp":215831,"x":535,"y":380},{"timeStamp":215851,"x":208,"y":343},{"timeStamp":215867,"x":535,"y":380},{"timeStamp":215886,"x":208,"y":343},{"timeStamp":215905,"x":535,"y":380},{"timeStamp":215922,"x":208,"y":343},{"timeStamp":215941,"x":535,"y":380},{"timeStamp":215958,"x":208,"y":343},{"timeStamp":215980,"x":535,"y":380},{"timeStamp":215998,"x":208,"y":343},{"timeStamp":216016,"x":535,"y":380},{"timeStamp":216033,"x":208,"y":343},{"timeStamp":216050,"x":535,"y":380},{"timeStamp":216067,"x":208,"y":343},{"timeStamp":216084,"x":535,"y":380},{"timeStamp":216101,"x":208,"y":343},{"timeStamp":216118,"x":535,"y":380},{"timeStamp":216139,"x":208,"y":343},{"timeStamp":216155,"x":535,"y":380},{"timeStamp":216172,"x":208,"y":343},{"timeStamp":216190,"x":535,"y":380},{"timeStamp":216210.00000000006,"x":208,"y":343},{"timeStamp":216228,"x":535,"y":380},{"timeStamp":216247,"x":208,"y":343},{"timeStamp":216269,"x":535,"y":380},{"timeStamp":216292,"x":208,"y":343}],"xPos":710.83,"yPos":710,"pointNumber":27},{"gazeData":[{"timeStamp":217815,"x":535,"y":380},{"timeStamp":217871.00000000006,"x":208,"y":343},{"timeStamp":217899,"x":535,"y":380},{"timeStamp":217924.00000000006,"x":208,"y":343},{"timeStamp":217949,"x":535,"y":380},{"timeStamp":217972.00000000006,"x":208,"y":343},{"timeStamp":217996.00000000006,"x":535,"y":380},{"timeStamp":218016,"x":208,"y":343},{"timeStamp":218034,"x":535,"y":380},{"timeStamp":218051,"x":208,"y":343},{"timeStamp":218072,"x":535,"y":380},{"timeStamp":218089,"x":208,"y":343},{"timeStamp":218106,"x":535,"y":380},{"timeStamp":218122,"x":208,"y":343},{"timeStamp":218144,"x":535,"y":380},{"timeStamp":218161,"x":208,"y":343},{"timeStamp":218180,"x":535,"y":380},{"timeStamp":218198.00000000006,"x":208,"y":343},{"timeStamp":218215,"x":535,"y":380},{"timeStamp":218234.00000000006,"x":208,"y":343},{"timeStamp":218250,"x":535,"y":380},{"timeStamp":218268,"x":208,"y":343},{"timeStamp":218285,"x":535,"y":380},{"timeStamp":218306,"x":208,"y":343},{"timeStamp":218323.00000000006,"x":535,"y":380},{"timeStamp":218342,"x":208,"y":343},{"timeStamp":218361,"x":535,"y":380},{"timeStamp":218380,"x":208,"y":343},{"timeStamp":218398,"x":535,"y":380},{"timeStamp":218414,"x":208,"y":343},{"timeStamp":218433,"x":535,"y":380},{"timeStamp":218453,"x":208,"y":343},{"timeStamp":218471,"x":535,"y":380},{"timeStamp":218489.00000000006,"x":208,"y":343},{"timeStamp":218508,"x":535,"y":380},{"timeStamp":218525.00000000006,"x":208,"y":343},{"timeStamp":218543,"x":535,"y":380},{"timeStamp":218560,"x":208,"y":343},{"timeStamp":218579,"x":535,"y":380},{"timeStamp":218599,"x":208,"y":343},{"timeStamp":218618,"x":535,"y":380},{"timeStamp":218636,"x":208,"y":343},{"timeStamp":218654,"x":535,"y":380},{"timeStamp":218672,"x":208,"y":343},{"timeStamp":218690,"x":535,"y":380},{"timeStamp":218709,"x":208,"y":343},{"timeStamp":218726,"x":535,"y":380},{"timeStamp":218745,"x":208,"y":343},{"timeStamp":218765,"x":535,"y":380},{"timeStamp":218783,"x":208,"y":343},{"timeStamp":218801,"x":535,"y":380},{"timeStamp":218817,"x":208,"y":343},{"timeStamp":218834,"x":535,"y":380},{"timeStamp":218850,"x":208,"y":343},{"timeStamp":218869,"x":535,"y":380},{"timeStamp":218888.00000000006,"x":208,"y":343},{"timeStamp":218908,"x":535,"y":380},{"timeStamp":218925,"x":208,"y":343},{"timeStamp":218945,"x":535,"y":380},{"timeStamp":218964,"x":208,"y":343},{"timeStamp":218981,"x":535,"y":380},{"timeStamp":219001.00000000006,"x":208,"y":343},{"timeStamp":219022,"x":535,"y":380},{"timeStamp":219041,"x":208,"y":343},{"timeStamp":219059,"x":535,"y":380},{"timeStamp":219077,"x":208,"y":343},{"timeStamp":219094,"x":535,"y":380},{"timeStamp":219114.00000000006,"x":208,"y":343},{"timeStamp":219133,"x":535,"y":380},{"timeStamp":219149,"x":208,"y":343}],"xPos":710.83,"yPos":30,"pointNumber":28},{"gazeData":[{"timeStamp":220672,"x":535,"y":380},{"timeStamp":220737,"x":208,"y":343},{"timeStamp":220771,"x":535,"y":380},{"timeStamp":220797,"x":208,"y":343},{"timeStamp":220822,"x":535,"y":380},{"timeStamp":220850,"x":208,"y":343},{"timeStamp":220876.00000000006,"x":535,"y":380},{"timeStamp":220894,"x":208,"y":343},{"timeStamp":220912.00000000006,"x":535,"y":380},{"timeStamp":220929,"x":208,"y":343},{"timeStamp":220947,"x":535,"y":380},{"timeStamp":220963,"x":208,"y":343},{"timeStamp":220979,"x":535,"y":380},{"timeStamp":220998,"x":208,"y":343},{"timeStamp":221015,"x":535,"y":380},{"timeStamp":221033,"x":208,"y":343},{"timeStamp":221051,"x":535,"y":380},{"timeStamp":221071,"x":208,"y":343},{"timeStamp":221092,"x":535,"y":380},{"timeStamp":221111,"x":208,"y":343},{"timeStamp":221129,"x":535,"y":380},{"timeStamp":221146,"x":208,"y":343},{"timeStamp":221165,"x":535,"y":380},{"timeStamp":221184,"x":208,"y":343},{"timeStamp":221203,"x":535,"y":380},{"timeStamp":221222.00000000006,"x":208,"y":343},{"timeStamp":221241,"x":535,"y":380},{"timeStamp":221258,"x":208,"y":343},{"timeStamp":221277,"x":535,"y":380},{"timeStamp":221295,"x":208,"y":343},{"timeStamp":221314,"x":535,"y":380},{"timeStamp":221333,"x":208,"y":343},{"timeStamp":221352,"x":535,"y":380},{"timeStamp":221369,"x":208,"y":343},{"timeStamp":221385,"x":535,"y":380},{"timeStamp":221404,"x":208,"y":343},{"timeStamp":221421,"x":535,"y":380},{"timeStamp":221439,"x":208,"y":343},{"timeStamp":221456,"x":535,"y":380},{"timeStamp":221474,"x":208,"y":343},{"timeStamp":221493,"x":535,"y":380},{"timeStamp":221513.00000000006,"x":208,"y":343},{"timeStamp":221530,"x":535,"y":380},{"timeStamp":221547,"x":208,"y":343},{"timeStamp":221566,"x":535,"y":380},{"timeStamp":221582,"x":208,"y":343},{"timeStamp":221599,"x":535,"y":380},{"timeStamp":221615,"x":208,"y":343},{"timeStamp":221635,"x":535,"y":380},{"timeStamp":221652,"x":208,"y":343},{"timeStamp":221671,"x":535,"y":380},{"timeStamp":221688,"x":208,"y":343},{"timeStamp":221706,"x":535,"y":380},{"timeStamp":221725,"x":208,"y":343},{"timeStamp":221744,"x":535,"y":380},{"timeStamp":221761,"x":208,"y":343},{"timeStamp":221778,"x":535,"y":380},{"timeStamp":221797,"x":208,"y":343},{"timeStamp":221815,"x":535,"y":380},{"timeStamp":221832,"x":208,"y":343},{"timeStamp":221848,"x":535,"y":380},{"timeStamp":221865,"x":208,"y":343},{"timeStamp":221881,"x":535,"y":380},{"timeStamp":221900.00000000006,"x":208,"y":343},{"timeStamp":221920,"x":535,"y":380},{"timeStamp":221938,"x":208,"y":343}],"xPos":166.17,"yPos":370,"pointNumber":29},{"gazeData":[{"timeStamp":223460.00000000006,"x":535,"y":380},{"timeStamp":223521,"x":208,"y":343},{"timeStamp":223550,"x":535,"y":380},{"timeStamp":223578,"x":208,"y":343},{"timeStamp":223606,"x":535,"y":380},{"timeStamp":223631,"x":208,"y":343},{"timeStamp":223651,"x":535,"y":380},{"timeStamp":223670,"x":208,"y":343},{"timeStamp":223689,"x":535,"y":380},{"timeStamp":223710.00000000006,"x":208,"y":343},{"timeStamp":223726,"x":535,"y":380},{"timeStamp":223743,"x":208,"y":343},{"timeStamp":223760,"x":535,"y":380},{"timeStamp":223777,"x":208,"y":343},{"timeStamp":223795,"x":535,"y":380},{"timeStamp":223814,"x":208,"y":343},{"timeStamp":223833,"x":535,"y":380},{"timeStamp":223852,"x":208,"y":343},{"timeStamp":223871.00000000006,"x":535,"y":380},{"timeStamp":223888.00000000006,"x":208,"y":343},{"timeStamp":223908,"x":535,"y":380},{"timeStamp":223925,"x":208,"y":343},{"timeStamp":223943,"x":535,"y":380},{"timeStamp":223960.00000000006,"x":208,"y":343},{"timeStamp":223982,"x":535,"y":380},{"timeStamp":224001.00000000006,"x":208,"y":343},{"timeStamp":224019,"x":535,"y":380},{"timeStamp":224038,"x":208,"y":343},{"timeStamp":224054,"x":535,"y":380},{"timeStamp":224071,"x":208,"y":343},{"timeStamp":224087,"x":535,"y":380},{"timeStamp":224106,"x":208,"y":343},{"timeStamp":224122,"x":535,"y":380},{"timeStamp":224140,"x":208,"y":343},{"timeStamp":224157,"x":535,"y":380},{"timeStamp":224175,"x":208,"y":343},{"timeStamp":224194,"x":535,"y":380},{"timeStamp":224211,"x":208,"y":343},{"timeStamp":224229,"x":535,"y":380},{"timeStamp":224248,"x":208,"y":343},{"timeStamp":224267,"x":535,"y":380},{"timeStamp":224285,"x":208,"y":343},{"timeStamp":224303,"x":535,"y":380},{"timeStamp":224321,"x":208,"y":343},{"timeStamp":224340,"x":535,"y":380},{"timeStamp":224357,"x":208,"y":343},{"timeStamp":224375,"x":535,"y":380},{"timeStamp":224395,"x":208,"y":343},{"timeStamp":224411,"x":535,"y":380},{"timeStamp":224431,"x":208,"y":343},{"timeStamp":224449,"x":535,"y":380},{"timeStamp":224469,"x":208,"y":343},{"timeStamp":224486,"x":535,"y":380},{"timeStamp":224503,"x":208,"y":343},{"timeStamp":224521,"x":535,"y":380},{"timeStamp":224540,"x":208,"y":343},{"timeStamp":224561.00000000006,"x":535,"y":380},{"timeStamp":224579,"x":208,"y":343},{"timeStamp":224598,"x":535,"y":380},{"timeStamp":224616,"x":208,"y":343},{"timeStamp":224634,"x":535,"y":380},{"timeStamp":224651,"x":208,"y":343},{"timeStamp":224670,"x":535,"y":380},{"timeStamp":224690,"x":208,"y":343},{"timeStamp":224710.00000000006,"x":535,"y":380},{"timeStamp":224727,"x":208,"y":343},{"timeStamp":224747,"x":535,"y":380},{"timeStamp":224766,"x":208,"y":343},{"timeStamp":224784,"x":535,"y":380},{"timeStamp":224803,"x":208,"y":343},{"timeStamp":224819,"x":535,"y":380}],"xPos":438.5,"yPos":370,"pointNumber":30},{"gazeData":[{"timeStamp":226345,"x":208,"y":343},{"timeStamp":226404,"x":535,"y":380},{"timeStamp":226434,"x":208,"y":343},{"timeStamp":226457,"x":535,"y":380},{"timeStamp":226482,"x":208,"y":343},{"timeStamp":226507,"x":535,"y":380},{"timeStamp":226529,"x":208,"y":343},{"timeStamp":226546,"x":535,"y":380},{"timeStamp":226565,"x":208,"y":343},{"timeStamp":226586,"x":535,"y":380},{"timeStamp":226607,"x":208,"y":343},{"timeStamp":226624,"x":535,"y":380},{"timeStamp":226641,"x":208,"y":343},{"timeStamp":226660,"x":535,"y":380},{"timeStamp":226678,"x":208,"y":343},{"timeStamp":226697,"x":535,"y":380},{"timeStamp":226715,"x":208,"y":343},{"timeStamp":226736,"x":535,"y":380},{"timeStamp":226753,"x":208,"y":343},{"timeStamp":226772,"x":535,"y":380},{"timeStamp":226792,"x":208,"y":343},{"timeStamp":226811.00000000006,"x":535,"y":380},{"timeStamp":226827,"x":208,"y":343},{"timeStamp":226844,"x":535,"y":380},{"timeStamp":226862,"x":208,"y":343},{"timeStamp":226879,"x":535,"y":380},{"timeStamp":226897,"x":208,"y":343},{"timeStamp":226913,"x":535,"y":380},{"timeStamp":226931,"x":208,"y":343},{"timeStamp":226948.00000000006,"x":535,"y":380},{"timeStamp":226967,"x":208,"y":343},{"timeStamp":226986,"x":535,"y":380},{"timeStamp":227004,"x":208,"y":343},{"timeStamp":227022,"x":535,"y":380},{"timeStamp":227041,"x":208,"y":343},{"timeStamp":227059,"x":535,"y":380},{"timeStamp":227078,"x":208,"y":343},{"timeStamp":227096,"x":535,"y":380},{"timeStamp":227113,"x":208,"y":343},{"timeStamp":227132,"x":535,"y":380},{"timeStamp":227149,"x":208,"y":343},{"timeStamp":227166,"x":535,"y":380},{"timeStamp":227183,"x":208,"y":343},{"timeStamp":227202,"x":535,"y":380},{"timeStamp":227220,"x":208,"y":343},{"timeStamp":227239.00000000006,"x":535,"y":380},{"timeStamp":227261,"x":208,"y":343},{"timeStamp":227278,"x":535,"y":380},{"timeStamp":227298,"x":208,"y":343},{"timeStamp":227315,"x":535,"y":380},{"timeStamp":227335.00000000006,"x":208,"y":343},{"timeStamp":227352,"x":535,"y":380},{"timeStamp":227371.00000000006,"x":208,"y":343},{"timeStamp":227387,"x":535,"y":380},{"timeStamp":227406,"x":208,"y":343},{"timeStamp":227427,"x":535,"y":380},{"timeStamp":227446,"x":208,"y":343},{"timeStamp":227462,"x":535,"y":380},{"timeStamp":227479,"x":208,"y":343},{"timeStamp":227495,"x":535,"y":380},{"timeStamp":227512,"x":208,"y":343},{"timeStamp":227530,"x":535,"y":380},{"timeStamp":227551,"x":208,"y":343},{"timeStamp":227568,"x":535,"y":380},{"timeStamp":227585.00000000006,"x":208,"y":343},{"timeStamp":227604,"x":535,"y":380}],"xPos":166.17,"yPos":30,"pointNumber":31},{"gazeData":[{"timeStamp":229128,"x":208,"y":343},{"timeStamp":229187,"x":535,"y":380},{"timeStamp":229217,"x":208,"y":343},{"timeStamp":229244,"x":535,"y":380},{"timeStamp":229269,"x":208,"y":343},{"timeStamp":229295,"x":535,"y":380},{"timeStamp":229321,"x":208,"y":343},{"timeStamp":229343,"x":535,"y":380},{"timeStamp":229360,"x":208,"y":343},{"timeStamp":229378,"x":535,"y":380},{"timeStamp":229397,"x":208,"y":343},{"timeStamp":229415,"x":535,"y":380},{"timeStamp":229435,"x":208,"y":343},{"timeStamp":229452,"x":535,"y":380},{"timeStamp":229472.00000000006,"x":208,"y":343},{"timeStamp":229491,"x":535,"y":380},{"timeStamp":229509,"x":208,"y":343},{"timeStamp":229529,"x":535,"y":380},{"timeStamp":229546,"x":208,"y":343},{"timeStamp":229565,"x":535,"y":380},{"timeStamp":229582,"x":208,"y":343},{"timeStamp":229601,"x":535,"y":380},{"timeStamp":229620,"x":208,"y":343},{"timeStamp":229638.00000000006,"x":535,"y":380},{"timeStamp":229658,"x":208,"y":343},{"timeStamp":229676,"x":535,"y":380},{"timeStamp":229695,"x":208,"y":343},{"timeStamp":229712,"x":535,"y":380},{"timeStamp":229732,"x":208,"y":343},{"timeStamp":229748,"x":535,"y":380},{"timeStamp":229771,"x":208,"y":343},{"timeStamp":229788,"x":535,"y":380},{"timeStamp":229807,"x":208,"y":343},{"timeStamp":229825,"x":535,"y":380},{"timeStamp":229843,"x":208,"y":343},{"timeStamp":229862,"x":535,"y":380},{"timeStamp":229879,"x":208,"y":343},{"timeStamp":229898,"x":535,"y":380},{"timeStamp":229916,"x":208,"y":343},{"timeStamp":229935,"x":535,"y":380},{"timeStamp":229952,"x":208,"y":343},{"timeStamp":229971,"x":535,"y":380},{"timeStamp":229988,"x":208,"y":343},{"timeStamp":230008,"x":535,"y":380},{"timeStamp":230025.00000000006,"x":208,"y":343},{"timeStamp":230043,"x":535,"y":380},{"timeStamp":230062,"x":208,"y":343},{"timeStamp":230079,"x":535,"y":380},{"timeStamp":230100,"x":208,"y":343},{"timeStamp":230117,"x":535,"y":380},{"timeStamp":230134,"x":208,"y":343},{"timeStamp":230152,"x":535,"y":380},{"timeStamp":230170,"x":208,"y":343},{"timeStamp":230186.00000000006,"x":535,"y":380},{"timeStamp":230205,"x":208,"y":343},{"timeStamp":230222.00000000006,"x":535,"y":380},{"timeStamp":230242,"x":208,"y":343},{"timeStamp":230262,"x":535,"y":380},{"timeStamp":230279,"x":208,"y":343},{"timeStamp":230298,"x":535,"y":380},{"timeStamp":230314,"x":208,"y":343},{"timeStamp":230333,"x":535,"y":380},{"timeStamp":230350,"x":208,"y":343},{"timeStamp":230369,"x":535,"y":380},{"timeStamp":230388.00000000006,"x":208,"y":343},{"timeStamp":230405,"x":535,"y":380},{"timeStamp":230422,"x":208,"y":343},{"timeStamp":230439,"x":535,"y":380},{"timeStamp":230455,"x":208,"y":343},{"timeStamp":230472.00000000006,"x":535,"y":380}],"xPos":710.83,"yPos":370,"pointNumber":32}],"dimensions":{"x":0,"y":0,"h":740,"w":877},"time":"2021-09-10 20:37:54"},{"readings":[{"gazeData":[{"timeStamp":344137,"x":438,"y":369},{"timeStamp":344205,"x":438,"y":369},{"timeStamp":344234.00000000006,"x":438,"y":369},{"timeStamp":344259,"x":438,"y":369},{"timeStamp":344284,"x":438,"y":369},{"timeStamp":344309,"x":438,"y":369},{"timeStamp":344332,"x":438,"y":369},{"timeStamp":344356,"x":438,"y":369},{"timeStamp":344373,"x":438,"y":369},{"timeStamp":344393,"x":438,"y":369},{"timeStamp":344409,"x":438,"y":369},{"timeStamp":344426,"x":438,"y":369},{"timeStamp":344444,"x":438,"y":369},{"timeStamp":344462,"x":438,"y":369},{"timeStamp":344479,"x":438,"y":369},{"timeStamp":344496.00000000006,"x":438,"y":369},{"timeStamp":344513.00000000006,"x":438,"y":369},{"timeStamp":344531,"x":438,"y":369},{"timeStamp":344551,"x":438,"y":369},{"timeStamp":344568,"x":438,"y":369},{"timeStamp":344586,"x":438,"y":369},{"timeStamp":344603,"x":438,"y":369},{"timeStamp":344622,"x":438,"y":369},{"timeStamp":344638.00000000006,"x":438,"y":369},{"timeStamp":344658,"x":438,"y":369},{"timeStamp":344675,"x":438,"y":369},{"timeStamp":344694,"x":438,"y":369},{"timeStamp":344712,"x":438,"y":369},{"timeStamp":344731,"x":438,"y":369},{"timeStamp":344747,"x":438,"y":369},{"timeStamp":344764,"x":438,"y":369},{"timeStamp":344781,"x":438,"y":369},{"timeStamp":344799.00000000006,"x":438,"y":369},{"timeStamp":344818,"x":438,"y":369},{"timeStamp":344835.00000000006,"x":438,"y":369},{"timeStamp":344855,"x":438,"y":369},{"timeStamp":344871.00000000006,"x":438,"y":369},{"timeStamp":344890,"x":438,"y":369},{"timeStamp":344907.00000000006,"x":438,"y":369},{"timeStamp":344924.00000000006,"x":438,"y":369},{"timeStamp":344941,"x":438,"y":369},{"timeStamp":344959,"x":438,"y":369},{"timeStamp":344978,"x":438,"y":369},{"timeStamp":344997,"x":438,"y":369},{"timeStamp":345014,"x":438,"y":369},{"timeStamp":345031,"x":438,"y":369},{"timeStamp":345047,"x":438,"y":369},{"timeStamp":345065,"x":438,"y":369},{"timeStamp":345083,"x":438,"y":369},{"timeStamp":345099,"x":438,"y":369},{"timeStamp":345121.00000000006,"x":438,"y":369},{"timeStamp":345138.00000000006,"x":438,"y":369},{"timeStamp":345157.00000000006,"x":438,"y":369},{"timeStamp":345174.00000000006,"x":438,"y":369},{"timeStamp":345194,"x":438,"y":369},{"timeStamp":345210.00000000006,"x":438,"y":369},{"timeStamp":345228,"x":438,"y":369},{"timeStamp":345244,"x":438,"y":369},{"timeStamp":345263.00000000006,"x":438,"y":369},{"timeStamp":345281,"x":438,"y":369},{"timeStamp":345298,"x":438,"y":369},{"timeStamp":345314,"x":438,"y":369},{"timeStamp":345332,"x":438,"y":369},{"timeStamp":345350,"x":438,"y":369},{"timeStamp":345366,"x":438,"y":369},{"timeStamp":345383.00000000006,"x":438,"y":369},{"timeStamp":345404,"x":438,"y":369},{"timeStamp":345420,"x":438,"y":369},{"timeStamp":345437,"x":438,"y":369},{"timeStamp":345456,"x":438,"y":369},{"timeStamp":345473,"x":438,"y":369},{"timeStamp":345492,"x":438,"y":369},{"timeStamp":345509,"x":438,"y":369},{"timeStamp":345528,"x":438,"y":369},{"timeStamp":345544.00000000006,"x":438,"y":369},{"timeStamp":345563,"x":438,"y":369}],"xPos":166.17,"yPos":710,"pointNumber":26},{"gazeData":[{"timeStamp":347083,"x":438,"y":369},{"timeStamp":347139,"x":438,"y":369},{"timeStamp":347169.00000000006,"x":438,"y":369},{"timeStamp":347195,"x":438,"y":369},{"timeStamp":347219,"x":438,"y":369},{"timeStamp":347241,"x":438,"y":369},{"timeStamp":347260,"x":438,"y":369},{"timeStamp":347279,"x":438,"y":369},{"timeStamp":347297,"x":438,"y":369},{"timeStamp":347317,"x":438,"y":369},{"timeStamp":347335.00000000006,"x":438,"y":369},{"timeStamp":347355,"x":438,"y":369},{"timeStamp":347372,"x":438,"y":369},{"timeStamp":347391,"x":438,"y":369},{"timeStamp":347408,"x":438,"y":369},{"timeStamp":347427,"x":438,"y":369},{"timeStamp":347446,"x":438,"y":369},{"timeStamp":347464,"x":438,"y":369},{"timeStamp":347485,"x":438,"y":369},{"timeStamp":347503,"x":438,"y":369},{"timeStamp":347521,"x":438,"y":369},{"timeStamp":347538,"x":438,"y":369},{"timeStamp":347559,"x":438,"y":369},{"timeStamp":347585.00000000006,"x":438,"y":369},{"timeStamp":347601,"x":438,"y":369},{"timeStamp":347621.00000000006,"x":438,"y":369},{"timeStamp":347637,"x":438,"y":369},{"timeStamp":347655,"x":438,"y":369},{"timeStamp":347674.00000000006,"x":438,"y":369},{"timeStamp":347692,"x":438,"y":369},{"timeStamp":347710.00000000006,"x":438,"y":369},{"timeStamp":347731,"x":438,"y":369},{"timeStamp":347750,"x":438,"y":369},{"timeStamp":347768,"x":438,"y":369},{"timeStamp":347787.00000000006,"x":438,"y":369},{"timeStamp":347803,"x":438,"y":369},{"timeStamp":347821,"x":438,"y":369},{"timeStamp":347838,"x":438,"y":369},{"timeStamp":347857,"x":438,"y":369},{"timeStamp":347874,"x":438,"y":369},{"timeStamp":347893,"x":438,"y":369},{"timeStamp":347909,"x":438,"y":369},{"timeStamp":347927,"x":438,"y":369},{"timeStamp":347946,"x":438,"y":369},{"timeStamp":347964,"x":438,"y":369},{"timeStamp":347982,"x":438,"y":369},{"timeStamp":347998,"x":438,"y":369},{"timeStamp":348017,"x":438,"y":369},{"timeStamp":348034,"x":438,"y":369},{"timeStamp":348053,"x":438,"y":369},{"timeStamp":348070,"x":438,"y":369},{"timeStamp":348088,"x":438,"y":369},{"timeStamp":348106,"x":438,"y":369},{"timeStamp":348125,"x":438,"y":369},{"timeStamp":348142,"x":438,"y":369},{"timeStamp":348162.00000000006,"x":438,"y":369},{"timeStamp":348179,"x":438,"y":369},{"timeStamp":348196,"x":438,"y":369},{"timeStamp":348213,"x":438,"y":369},{"timeStamp":348230,"x":438,"y":369},{"timeStamp":348248,"x":438,"y":369},{"timeStamp":348265,"x":438,"y":369},{"timeStamp":348282.00000000006,"x":438,"y":369},{"timeStamp":348298,"x":438,"y":369},{"timeStamp":348318.00000000006,"x":438,"y":369},{"timeStamp":348334,"x":438,"y":369},{"timeStamp":348353,"x":438,"y":369},{"timeStamp":348370,"x":438,"y":369},{"timeStamp":348389,"x":438,"y":369},{"timeStamp":348406,"x":438,"y":369},{"timeStamp":348425,"x":438,"y":369},{"timeStamp":348442,"x":438,"y":369},{"timeStamp":348463,"x":438,"y":369},{"timeStamp":348480,"x":438,"y":369}],"xPos":710.83,"yPos":30,"pointNumber":27},{"gazeData":[{"timeStamp":350003,"x":438,"y":369},{"timeStamp":350055,"x":438,"y":369},{"timeStamp":350086,"x":438,"y":369},{"timeStamp":350112,"x":438,"y":369},{"timeStamp":350137,"x":438,"y":369},{"timeStamp":350159,"x":438,"y":369},{"timeStamp":350178,"x":438,"y":369},{"timeStamp":350196,"x":438,"y":369},{"timeStamp":350215,"x":438,"y":369},{"timeStamp":350234.00000000006,"x":438,"y":369},{"timeStamp":350253,"x":438,"y":369},{"timeStamp":350271,"x":438,"y":369},{"timeStamp":350290,"x":438,"y":369},{"timeStamp":350307,"x":438,"y":369},{"timeStamp":350326,"x":438,"y":369},{"timeStamp":350345,"x":438,"y":369},{"timeStamp":350363,"x":438,"y":369},{"timeStamp":350383.00000000006,"x":438,"y":369},{"timeStamp":350400.00000000006,"x":438,"y":369},{"timeStamp":350419.00000000006,"x":438,"y":369},{"timeStamp":350436.00000000006,"x":438,"y":369},{"timeStamp":350455,"x":438,"y":369},{"timeStamp":350472.00000000006,"x":438,"y":369},{"timeStamp":350491,"x":438,"y":369},{"timeStamp":350508.00000000006,"x":438,"y":369},{"timeStamp":350527,"x":438,"y":369},{"timeStamp":350548,"x":438,"y":369},{"timeStamp":350565,"x":438,"y":369},{"timeStamp":350584,"x":438,"y":369},{"timeStamp":350602,"x":438,"y":369},{"timeStamp":350622,"x":438,"y":369},{"timeStamp":350639,"x":438,"y":369},{"timeStamp":350661,"x":438,"y":369},{"timeStamp":350679,"x":438,"y":369},{"timeStamp":350697,"x":438,"y":369},{"timeStamp":350716,"x":438,"y":369},{"timeStamp":350733,"x":438,"y":369},{"timeStamp":350753,"x":438,"y":369},{"timeStamp":350770.00000000006,"x":438,"y":369},{"timeStamp":350788,"x":438,"y":369},{"timeStamp":350806.00000000006,"x":438,"y":369},{"timeStamp":350826,"x":438,"y":369},{"timeStamp":350845,"x":438,"y":369},{"timeStamp":350863,"x":438,"y":369},{"timeStamp":350880,"x":438,"y":369},{"timeStamp":350897,"x":438,"y":369},{"timeStamp":350916,"x":438,"y":369},{"timeStamp":350934,"x":438,"y":369},{"timeStamp":350953,"x":438,"y":369},{"timeStamp":350971,"x":438,"y":369},{"timeStamp":350991,"x":438,"y":369},{"timeStamp":351011,"x":438,"y":369},{"timeStamp":351028,"x":438,"y":369},{"timeStamp":351046,"x":438,"y":369},{"timeStamp":351064,"x":438,"y":369},{"timeStamp":351081,"x":438,"y":369},{"timeStamp":351097.00000000006,"x":438,"y":369},{"timeStamp":351113,"x":438,"y":369},{"timeStamp":351133.00000000006,"x":438,"y":369},{"timeStamp":351151,"x":438,"y":369},{"timeStamp":351168,"x":438,"y":369},{"timeStamp":351187,"x":438,"y":369},{"timeStamp":351205,"x":438,"y":369},{"timeStamp":351224,"x":438,"y":369},{"timeStamp":351243,"x":438,"y":369},{"timeStamp":351261,"x":438,"y":369}],"xPos":166.17,"yPos":370,"pointNumber":28},{"gazeData":[{"timeStamp":352783,"x":438,"y":369},{"timeStamp":352839,"x":438,"y":369},{"timeStamp":352867,"x":438,"y":369},{"timeStamp":352894,"x":438,"y":369},{"timeStamp":352917,"x":438,"y":369},{"timeStamp":352939,"x":438,"y":369},{"timeStamp":352960.00000000006,"x":438,"y":369},{"timeStamp":352979,"x":438,"y":369},{"timeStamp":352997,"x":438,"y":369},{"timeStamp":353015,"x":438,"y":369},{"timeStamp":353033,"x":438,"y":369},{"timeStamp":353051,"x":438,"y":369},{"timeStamp":353069,"x":438,"y":369},{"timeStamp":353088,"x":438,"y":369},{"timeStamp":353105,"x":438,"y":369},{"timeStamp":353123,"x":438,"y":369},{"timeStamp":353144,"x":438,"y":369},{"timeStamp":353162.00000000006,"x":438,"y":369},{"timeStamp":353182,"x":438,"y":369},{"timeStamp":353198.00000000006,"x":438,"y":369},{"timeStamp":353217,"x":438,"y":369},{"timeStamp":353234.00000000006,"x":438,"y":369},{"timeStamp":353253,"x":438,"y":369},{"timeStamp":353269,"x":438,"y":369},{"timeStamp":353289,"x":438,"y":369},{"timeStamp":353308,"x":438,"y":369},{"timeStamp":353326,"x":438,"y":369},{"timeStamp":353343,"x":438,"y":369},{"timeStamp":353360,"x":438,"y":369},{"timeStamp":353376.00000000006,"x":438,"y":369},{"timeStamp":353393,"x":438,"y":369},{"timeStamp":353412.00000000006,"x":438,"y":369},{"timeStamp":353429,"x":438,"y":369},{"timeStamp":353449,"x":438,"y":369},{"timeStamp":353469,"x":438,"y":369},{"timeStamp":353488,"x":438,"y":369},{"timeStamp":353505,"x":438,"y":369},{"timeStamp":353523,"x":438,"y":369},{"timeStamp":353543,"x":438,"y":369},{"timeStamp":353560,"x":438,"y":369},{"timeStamp":353578,"x":438,"y":369},{"timeStamp":353595,"x":438,"y":369},{"timeStamp":353614.00000000006,"x":438,"y":369},{"timeStamp":353630,"x":438,"y":369},{"timeStamp":353649,"x":438,"y":369},{"timeStamp":353667,"x":438,"y":369},{"timeStamp":353686.00000000006,"x":438,"y":369},{"timeStamp":353702,"x":438,"y":369},{"timeStamp":353721,"x":438,"y":369},{"timeStamp":353739.00000000006,"x":438,"y":369},{"timeStamp":353758.00000000006,"x":438,"y":369},{"timeStamp":353777,"x":438,"y":369},{"timeStamp":353794.00000000006,"x":438,"y":369},{"timeStamp":353812,"x":438,"y":369},{"timeStamp":353830,"x":438,"y":369},{"timeStamp":353850,"x":438,"y":369},{"timeStamp":353868,"x":438,"y":369},{"timeStamp":353887,"x":438,"y":369},{"timeStamp":353907.00000000006,"x":438,"y":369},{"timeStamp":353927,"x":438,"y":369},{"timeStamp":353945,"x":438,"y":369},{"timeStamp":353962,"x":438,"y":369},{"timeStamp":353981,"x":438,"y":369},{"timeStamp":353998,"x":438,"y":369},{"timeStamp":354017,"x":438,"y":369},{"timeStamp":354034,"x":438,"y":369},{"timeStamp":354053,"x":438,"y":369},{"timeStamp":354072,"x":438,"y":369},{"timeStamp":354090,"x":438,"y":369},{"timeStamp":354109.00000000006,"x":438,"y":369}],"xPos":166.17,"yPos":30,"pointNumber":29},{"gazeData":[{"timeStamp":355632,"x":438,"y":369},{"timeStamp":355689,"x":438,"y":369},{"timeStamp":355718,"x":438,"y":369},{"timeStamp":355741,"x":438,"y":369},{"timeStamp":355765,"x":438,"y":369},{"timeStamp":355791,"x":438,"y":369},{"timeStamp":355822,"x":438,"y":369},{"timeStamp":355845,"x":438,"y":369},{"timeStamp":355863,"x":438,"y":369},{"timeStamp":355884,"x":438,"y":369},{"timeStamp":355902,"x":438,"y":369},{"timeStamp":355921,"x":438,"y":369},{"timeStamp":355937,"x":438,"y":369},{"timeStamp":355954,"x":438,"y":369},{"timeStamp":355971,"x":438,"y":369},{"timeStamp":355989.00000000006,"x":438,"y":369},{"timeStamp":356006,"x":438,"y":369},{"timeStamp":356025.00000000006,"x":438,"y":369},{"timeStamp":356045,"x":438,"y":369},{"timeStamp":356062,"x":438,"y":369},{"timeStamp":356080,"x":438,"y":369},{"timeStamp":356096,"x":438,"y":369},{"timeStamp":356114.00000000006,"x":438,"y":369},{"timeStamp":356131,"x":438,"y":369},{"timeStamp":356150.00000000006,"x":438,"y":369},{"timeStamp":356168,"x":438,"y":369},{"timeStamp":356187,"x":438,"y":369},{"timeStamp":356204,"x":438,"y":369},{"timeStamp":356222.00000000006,"x":438,"y":369},{"timeStamp":356240,"x":438,"y":369},{"timeStamp":356259,"x":438,"y":369},{"timeStamp":356277,"x":438,"y":369},{"timeStamp":356295,"x":438,"y":369},{"timeStamp":356314,"x":438,"y":369},{"timeStamp":356331,"x":438,"y":369},{"timeStamp":356349,"x":438,"y":369},{"timeStamp":356366,"x":438,"y":369},{"timeStamp":356385,"x":438,"y":369},{"timeStamp":356403,"x":438,"y":369},{"timeStamp":356422,"x":438,"y":369},{"timeStamp":356444,"x":438,"y":369},{"timeStamp":356462,"x":438,"y":369},{"timeStamp":356481,"x":438,"y":369},{"timeStamp":356498,"x":438,"y":369},{"timeStamp":356516,"x":438,"y":369},{"timeStamp":356533,"x":438,"y":369},{"timeStamp":356553,"x":438,"y":369},{"timeStamp":356575,"x":438,"y":369},{"timeStamp":356592,"x":438,"y":369},{"timeStamp":356609.00000000006,"x":438,"y":369},{"timeStamp":356626.00000000006,"x":438,"y":369},{"timeStamp":356644,"x":438,"y":369},{"timeStamp":356660,"x":438,"y":369},{"timeStamp":356679,"x":438,"y":369},{"timeStamp":356695,"x":438,"y":369},{"timeStamp":356712,"x":438,"y":369},{"timeStamp":356728,"x":438,"y":369},{"timeStamp":356745,"x":438,"y":369},{"timeStamp":356762,"x":438,"y":369},{"timeStamp":356781,"x":438,"y":369},{"timeStamp":356798,"x":438,"y":369},{"timeStamp":356817,"x":438,"y":369},{"timeStamp":356835.00000000006,"x":438,"y":369},{"timeStamp":356854,"x":438,"y":369},{"timeStamp":356870,"x":438,"y":369},{"timeStamp":356889,"x":438,"y":369}],"xPos":710.83,"yPos":710,"pointNumber":30},{"gazeData":[{"timeStamp":358414,"x":438,"y":369},{"timeStamp":358472.00000000006,"x":438,"y":369},{"timeStamp":358503,"x":438,"y":369},{"timeStamp":358530,"x":438,"y":369},{"timeStamp":358553,"x":438,"y":369},{"timeStamp":358579,"x":438,"y":369},{"timeStamp":358598,"x":438,"y":369},{"timeStamp":358615,"x":438,"y":369},{"timeStamp":358633.00000000006,"x":438,"y":369},{"timeStamp":358655,"x":438,"y":369},{"timeStamp":358672,"x":438,"y":369},{"timeStamp":358691,"x":438,"y":369},{"timeStamp":358709,"x":438,"y":369},{"timeStamp":358725,"x":438,"y":369},{"timeStamp":358742,"x":438,"y":369},{"timeStamp":358760,"x":438,"y":369},{"timeStamp":358778,"x":438,"y":369},{"timeStamp":358798,"x":438,"y":369},{"timeStamp":358817,"x":438,"y":369},{"timeStamp":358834,"x":438,"y":369},{"timeStamp":358852,"x":438,"y":369},{"timeStamp":358869,"x":438,"y":369},{"timeStamp":358888.00000000006,"x":438,"y":369},{"timeStamp":358907.00000000006,"x":438,"y":369},{"timeStamp":358925,"x":438,"y":369},{"timeStamp":358942,"x":438,"y":369},{"timeStamp":358961,"x":438,"y":369},{"timeStamp":358979,"x":438,"y":369},{"timeStamp":358996.00000000006,"x":438,"y":369},{"timeStamp":359014,"x":438,"y":369},{"timeStamp":359031,"x":438,"y":369},{"timeStamp":359047,"x":438,"y":369},{"timeStamp":359066,"x":438,"y":369},{"timeStamp":359085.00000000006,"x":438,"y":369},{"timeStamp":359102,"x":438,"y":369},{"timeStamp":359121.00000000006,"x":438,"y":369},{"timeStamp":359138.00000000006,"x":438,"y":369},{"timeStamp":359155,"x":438,"y":369},{"timeStamp":359174.00000000006,"x":438,"y":369},{"timeStamp":359192,"x":438,"y":369},{"timeStamp":359208,"x":438,"y":369},{"timeStamp":359227,"x":438,"y":369},{"timeStamp":359245,"x":438,"y":369},{"timeStamp":359261,"x":438,"y":369},{"timeStamp":359280,"x":438,"y":369},{"timeStamp":359297,"x":438,"y":369},{"timeStamp":359316,"x":438,"y":369},{"timeStamp":359333,"x":438,"y":369},{"timeStamp":359355,"x":438,"y":369},{"timeStamp":359371.00000000006,"x":438,"y":369},{"timeStamp":359390,"x":438,"y":369},{"timeStamp":359407.00000000006,"x":438,"y":369},{"timeStamp":359425,"x":438,"y":369},{"timeStamp":359441,"x":438,"y":369},{"timeStamp":359457,"x":438,"y":369},{"timeStamp":359475,"x":438,"y":369},{"timeStamp":359494,"x":438,"y":369},{"timeStamp":359512,"x":438,"y":369},{"timeStamp":359529,"x":438,"y":369},{"timeStamp":359548,"x":438,"y":369},{"timeStamp":359565,"x":438,"y":369},{"timeStamp":359584,"x":438,"y":369},{"timeStamp":359601,"x":438,"y":369},{"timeStamp":359620,"x":438,"y":369},{"timeStamp":359639,"x":438,"y":369},{"timeStamp":359659,"x":438,"y":369},{"timeStamp":359677,"x":438,"y":369},{"timeStamp":359694,"x":438,"y":369},{"timeStamp":359710.00000000006,"x":438,"y":369},{"timeStamp":359727,"x":438,"y":369}],"xPos":438.5,"yPos":370,"pointNumber":31},{"gazeData":[{"timeStamp":361246.00000000006,"x":438,"y":369},{"timeStamp":361306.00000000006,"x":438,"y":369},{"timeStamp":361337,"x":438,"y":369},{"timeStamp":361363,"x":438,"y":369},{"timeStamp":361389,"x":438,"y":369},{"timeStamp":361414,"x":438,"y":369},{"timeStamp":361435,"x":438,"y":369},{"timeStamp":361457,"x":438,"y":369},{"timeStamp":361476,"x":438,"y":369},{"timeStamp":361493,"x":438,"y":369},{"timeStamp":361512,"x":438,"y":369},{"timeStamp":361528,"x":438,"y":369},{"timeStamp":361547,"x":438,"y":369},{"timeStamp":361564,"x":438,"y":369},{"timeStamp":361583,"x":438,"y":369},{"timeStamp":361600,"x":438,"y":369},{"timeStamp":361622,"x":438,"y":369},{"timeStamp":361641,"x":438,"y":369},{"timeStamp":361660,"x":438,"y":369},{"timeStamp":361679,"x":438,"y":369},{"timeStamp":361696,"x":438,"y":369},{"timeStamp":361712,"x":438,"y":369},{"timeStamp":361728,"x":438,"y":369},{"timeStamp":361747,"x":438,"y":369},{"timeStamp":361764,"x":438,"y":369},{"timeStamp":361782.00000000006,"x":438,"y":369},{"timeStamp":361799.00000000006,"x":438,"y":369},{"timeStamp":361818.00000000006,"x":438,"y":369},{"timeStamp":361835.00000000006,"x":438,"y":369},{"timeStamp":361854,"x":438,"y":369},{"timeStamp":361871.00000000006,"x":438,"y":369},{"timeStamp":361889,"x":438,"y":369},{"timeStamp":361908,"x":438,"y":369},{"timeStamp":361925,"x":438,"y":369},{"timeStamp":361944,"x":438,"y":369},{"timeStamp":361961,"x":438,"y":369},{"timeStamp":361980,"x":438,"y":369},{"timeStamp":361996.00000000006,"x":438,"y":369},{"timeStamp":362015,"x":438,"y":369},{"timeStamp":362032.00000000006,"x":438,"y":369},{"timeStamp":362052,"x":438,"y":369},{"timeStamp":362070,"x":438,"y":369},{"timeStamp":362089,"x":438,"y":369},{"timeStamp":362107,"x":438,"y":369},{"timeStamp":362125,"x":438,"y":369},{"timeStamp":362145.00000000006,"x":438,"y":369},{"timeStamp":362161,"x":438,"y":369},{"timeStamp":362180,"x":438,"y":369},{"timeStamp":362198.00000000006,"x":438,"y":369},{"timeStamp":362216,"x":438,"y":369},{"timeStamp":362234.00000000006,"x":438,"y":369},{"timeStamp":362252,"x":438,"y":369},{"timeStamp":362269,"x":438,"y":369},{"timeStamp":362287.00000000006,"x":438,"y":369},{"timeStamp":362304,"x":438,"y":369},{"timeStamp":362323.00000000006,"x":438,"y":369},{"timeStamp":362342,"x":438,"y":369},{"timeStamp":362362,"x":438,"y":369},{"timeStamp":362380,"x":438,"y":369},{"timeStamp":362397,"x":438,"y":369},{"timeStamp":362413,"x":438,"y":369},{"timeStamp":362430,"x":438,"y":369},{"timeStamp":362449,"x":438,"y":369},{"timeStamp":362466,"x":438,"y":369},{"timeStamp":362485,"x":438,"y":369},{"timeStamp":362504,"x":438,"y":369},{"timeStamp":362522,"x":438,"y":369},{"timeStamp":362541,"x":438,"y":369},{"timeStamp":362558,"x":438,"y":369},{"timeStamp":362577,"x":438,"y":369},{"timeStamp":362594,"x":438,"y":369},{"timeStamp":362613,"x":438,"y":369},{"timeStamp":362633.00000000006,"x":438,"y":369},{"timeStamp":362653,"x":438,"y":369},{"timeStamp":362670,"x":438,"y":369},{"timeStamp":362687,"x":438,"y":369}],"xPos":710.83,"yPos":370,"pointNumber":32}],"dimensions":{"x":0,"y":0,"h":848,"w":1152},"time":"2021-09-10 20:40:06"},{"readings":[{"gazeData":[{"timeStamp":460116,"x":575,"y":423},{"timeStamp":460173,"x":575,"y":423},{"timeStamp":460199,"x":575,"y":423},{"timeStamp":460225,"x":575,"y":423},{"timeStamp":460249,"x":575,"y":423},{"timeStamp":460274,"x":575,"y":423},{"timeStamp":460294,"x":575,"y":423},{"timeStamp":460312.0000000001,"x":575,"y":423},{"timeStamp":460329,"x":575,"y":423},{"timeStamp":460350,"x":575,"y":423},{"timeStamp":460367,"x":575,"y":423},{"timeStamp":460385,"x":575,"y":423},{"timeStamp":460402,"x":575,"y":423},{"timeStamp":460420,"x":575,"y":423},{"timeStamp":460437.0000000001,"x":575,"y":423},{"timeStamp":460453,"x":575,"y":423},{"timeStamp":460472,"x":575,"y":423},{"timeStamp":460498,"x":575,"y":423},{"timeStamp":460527,"x":575,"y":423},{"timeStamp":460553,"x":575,"y":423},{"timeStamp":460570,"x":575,"y":423},{"timeStamp":460587,"x":575,"y":423},{"timeStamp":460604,"x":575,"y":423},{"timeStamp":460621,"x":575,"y":423},{"timeStamp":460638,"x":575,"y":423},{"timeStamp":460654,"x":575,"y":423},{"timeStamp":460673,"x":575,"y":423},{"timeStamp":460690,"x":575,"y":423},{"timeStamp":460707,"x":575,"y":423},{"timeStamp":460723,"x":575,"y":423},{"timeStamp":460740.0000000001,"x":575,"y":423},{"timeStamp":460757,"x":575,"y":423},{"timeStamp":460774,"x":575,"y":423},{"timeStamp":460791,"x":575,"y":423},{"timeStamp":460812.0000000001,"x":575,"y":423},{"timeStamp":460829,"x":575,"y":423},{"timeStamp":460848,"x":575,"y":423},{"timeStamp":460866,"x":575,"y":423},{"timeStamp":460885,"x":575,"y":423},{"timeStamp":460904,"x":575,"y":423},{"timeStamp":460920,"x":575,"y":423},{"timeStamp":460939,"x":575,"y":423},{"timeStamp":460956,"x":575,"y":423},{"timeStamp":460975,"x":575,"y":423},{"timeStamp":460993,"x":575,"y":423},{"timeStamp":461012,"x":575,"y":423},{"timeStamp":461028,"x":575,"y":423},{"timeStamp":461047,"x":575,"y":423},{"timeStamp":461063,"x":575,"y":423},{"timeStamp":461083,"x":575,"y":423},{"timeStamp":461100,"x":575,"y":423},{"timeStamp":461118,"x":575,"y":423},{"timeStamp":461135,"x":575,"y":423},{"timeStamp":461152,"x":575,"y":423},{"timeStamp":461170,"x":575,"y":423},{"timeStamp":461188,"x":575,"y":423},{"timeStamp":461206,"x":575,"y":423},{"timeStamp":461224,"x":575,"y":423},{"timeStamp":461245,"x":575,"y":423},{"timeStamp":461262,"x":575,"y":423},{"timeStamp":461281,"x":575,"y":423},{"timeStamp":461298,"x":575,"y":423},{"timeStamp":461317.0000000001,"x":575,"y":423},{"timeStamp":461335,"x":575,"y":423},{"timeStamp":461353,"x":575,"y":423},{"timeStamp":461371,"x":575,"y":423},{"timeStamp":461389.0000000001,"x":575,"y":423},{"timeStamp":461407,"x":575,"y":423},{"timeStamp":461425,"x":575,"y":423},{"timeStamp":461444,"x":575,"y":423},{"timeStamp":461461.0000000001,"x":575,"y":423},{"timeStamp":461480,"x":575,"y":423},{"timeStamp":461496,"x":575,"y":423},{"timeStamp":461514.0000000001,"x":575,"y":423},{"timeStamp":461533,"x":575,"y":423}],"xPos":940,"yPos":30,"pointNumber":26},{"gazeData":[{"timeStamp":463058,"x":575,"y":423},{"timeStamp":463123,"x":575,"y":423},{"timeStamp":463153,"x":575,"y":423},{"timeStamp":463179,"x":575,"y":423},{"timeStamp":463205,"x":575,"y":423},{"timeStamp":463229,"x":575,"y":423},{"timeStamp":463252,"x":575,"y":423},{"timeStamp":463271,"x":575,"y":423},{"timeStamp":463289,"x":575,"y":423},{"timeStamp":463308,"x":575,"y":423},{"timeStamp":463326,"x":575,"y":423},{"timeStamp":463344,"x":575,"y":423},{"timeStamp":463361,"x":575,"y":423},{"timeStamp":463380,"x":575,"y":423},{"timeStamp":463396,"x":575,"y":423},{"timeStamp":463413.0000000001,"x":575,"y":423},{"timeStamp":463433,"x":575,"y":423},{"timeStamp":463451,"x":575,"y":423},{"timeStamp":463470,"x":575,"y":423},{"timeStamp":463488,"x":575,"y":423},{"timeStamp":463507,"x":575,"y":423},{"timeStamp":463523,"x":575,"y":423},{"timeStamp":463542,"x":575,"y":423},{"timeStamp":463559,"x":575,"y":423},{"timeStamp":463578,"x":575,"y":423},{"timeStamp":463596,"x":575,"y":423},{"timeStamp":463615.0000000001,"x":575,"y":423},{"timeStamp":463634,"x":575,"y":423},{"timeStamp":463652,"x":575,"y":423},{"timeStamp":463671,"x":575,"y":423},{"timeStamp":463687.0000000001,"x":575,"y":423},{"timeStamp":463705,"x":575,"y":423},{"timeStamp":463725,"x":575,"y":423},{"timeStamp":463744,"x":575,"y":423},{"timeStamp":463761,"x":575,"y":423},{"timeStamp":463778,"x":575,"y":423},{"timeStamp":463795,"x":575,"y":423},{"timeStamp":463813,"x":575,"y":423},{"timeStamp":463830,"x":575,"y":423},{"timeStamp":463849,"x":575,"y":423},{"timeStamp":463866,"x":575,"y":423},{"timeStamp":463886,"x":575,"y":423},{"timeStamp":463905,"x":575,"y":423},{"timeStamp":463922,"x":575,"y":423},{"timeStamp":463941,"x":575,"y":423},{"timeStamp":463958,"x":575,"y":423},{"timeStamp":463974,"x":575,"y":423},{"timeStamp":463991,"x":575,"y":423},{"timeStamp":464012,"x":575,"y":423},{"timeStamp":464029,"x":575,"y":423},{"timeStamp":464048,"x":575,"y":423},{"timeStamp":464065,"x":575,"y":423},{"timeStamp":464084,"x":575,"y":423},{"timeStamp":464101,"x":575,"y":423},{"timeStamp":464117,"x":575,"y":423},{"timeStamp":464134,"x":575,"y":423},{"timeStamp":464152,"x":575,"y":423},{"timeStamp":464173,"x":575,"y":423},{"timeStamp":464189,"x":575,"y":423},{"timeStamp":464204,"x":575,"y":423},{"timeStamp":464220,"x":575,"y":423},{"timeStamp":464238,"x":575,"y":423},{"timeStamp":464255,"x":575,"y":423},{"timeStamp":464274,"x":575,"y":423},{"timeStamp":464293.0000000001,"x":575,"y":423},{"timeStamp":464311,"x":575,"y":423},{"timeStamp":464327,"x":575,"y":423},{"timeStamp":464343,"x":575,"y":423},{"timeStamp":464360.0000000001,"x":575,"y":423},{"timeStamp":464379,"x":575,"y":423},{"timeStamp":464396,"x":575,"y":423},{"timeStamp":464414,"x":575,"y":423},{"timeStamp":464431,"x":575,"y":423},{"timeStamp":464450,"x":575,"y":423},{"timeStamp":464469,"x":575,"y":423},{"timeStamp":464486,"x":575,"y":423}],"xPos":940,"yPos":424,"pointNumber":27},{"gazeData":[{"timeStamp":466009,"x":575,"y":423},{"timeStamp":466073,"x":575,"y":423},{"timeStamp":466102,"x":575,"y":423},{"timeStamp":466127,"x":575,"y":423},{"timeStamp":466152,"x":575,"y":423},{"timeStamp":466178,"x":575,"y":423},{"timeStamp":466198,"x":575,"y":423},{"timeStamp":466215,"x":575,"y":423},{"timeStamp":466233,"x":575,"y":423},{"timeStamp":466252,"x":575,"y":423},{"timeStamp":466272,"x":575,"y":423},{"timeStamp":466289,"x":575,"y":423},{"timeStamp":466309,"x":575,"y":423},{"timeStamp":466326,"x":575,"y":423},{"timeStamp":466345,"x":575,"y":423},{"timeStamp":466364,"x":575,"y":423},{"timeStamp":466382,"x":575,"y":423},{"timeStamp":466399,"x":575,"y":423},{"timeStamp":466419,"x":575,"y":423},{"timeStamp":466438,"x":575,"y":423},{"timeStamp":466455,"x":575,"y":423},{"timeStamp":466474,"x":575,"y":423},{"timeStamp":466490.0000000001,"x":575,"y":423},{"timeStamp":466507,"x":575,"y":423},{"timeStamp":466524,"x":575,"y":423},{"timeStamp":466542,"x":575,"y":423},{"timeStamp":466562.0000000001,"x":575,"y":423},{"timeStamp":466581,"x":575,"y":423},{"timeStamp":466598,"x":575,"y":423},{"timeStamp":466615.0000000001,"x":575,"y":423},{"timeStamp":466634,"x":575,"y":423},{"timeStamp":466652,"x":575,"y":423},{"timeStamp":466671,"x":575,"y":423},{"timeStamp":466688,"x":575,"y":423},{"timeStamp":466707,"x":575,"y":423},{"timeStamp":466727,"x":575,"y":423},{"timeStamp":466746,"x":575,"y":423},{"timeStamp":466763,"x":575,"y":423},{"timeStamp":466782,"x":575,"y":423},{"timeStamp":466799,"x":575,"y":423},{"timeStamp":466817.0000000001,"x":575,"y":423},{"timeStamp":466833,"x":575,"y":423},{"timeStamp":466850,"x":575,"y":423},{"timeStamp":466866,"x":575,"y":423},{"timeStamp":466886,"x":575,"y":423},{"timeStamp":466904,"x":575,"y":423},{"timeStamp":466921,"x":575,"y":423},{"timeStamp":466939,"x":575,"y":423},{"timeStamp":466957,"x":575,"y":423},{"timeStamp":466975,"x":575,"y":423},{"timeStamp":466995,"x":575,"y":423},{"timeStamp":467014.0000000001,"x":575,"y":423},{"timeStamp":467030,"x":575,"y":423},{"timeStamp":467047,"x":575,"y":423},{"timeStamp":467064,"x":575,"y":423},{"timeStamp":467082,"x":575,"y":423},{"timeStamp":467099,"x":575,"y":423},{"timeStamp":467117,"x":575,"y":423},{"timeStamp":467136,"x":575,"y":423},{"timeStamp":467154,"x":575,"y":423},{"timeStamp":467173,"x":575,"y":423},{"timeStamp":467190,"x":575,"y":423},{"timeStamp":467209,"x":575,"y":423},{"timeStamp":467226,"x":575,"y":423},{"timeStamp":467245,"x":575,"y":423},{"timeStamp":467262,"x":575,"y":423},{"timeStamp":467281,"x":575,"y":423},{"timeStamp":467300,"x":575,"y":423},{"timeStamp":467318,"x":575,"y":423},{"timeStamp":467337,"x":575,"y":423},{"timeStamp":467353,"x":575,"y":423},{"timeStamp":467372,"x":575,"y":423}],"xPos":212,"yPos":818,"pointNumber":28},{"gazeData":[{"timeStamp":468897,"x":575,"y":423},{"timeStamp":468956,"x":575,"y":423},{"timeStamp":468984,"x":575,"y":423},{"timeStamp":469011,"x":575,"y":423},{"timeStamp":469036,"x":575,"y":423},{"timeStamp":469058,"x":575,"y":423},{"timeStamp":469080,"x":575,"y":423},{"timeStamp":469097,"x":575,"y":423},{"timeStamp":469115.0000000001,"x":575,"y":423},{"timeStamp":469134.0000000001,"x":575,"y":423},{"timeStamp":469152,"x":575,"y":423},{"timeStamp":469171,"x":575,"y":423},{"timeStamp":469188,"x":575,"y":423},{"timeStamp":469207,"x":575,"y":423},{"timeStamp":469224,"x":575,"y":423},{"timeStamp":469243,"x":575,"y":423},{"timeStamp":469263,"x":575,"y":423},{"timeStamp":469282,"x":575,"y":423},{"timeStamp":469299,"x":575,"y":423},{"timeStamp":469316,"x":575,"y":423},{"timeStamp":469335,"x":575,"y":423},{"timeStamp":469352,"x":575,"y":423},{"timeStamp":469372,"x":575,"y":423},{"timeStamp":469388,"x":575,"y":423},{"timeStamp":469406,"x":575,"y":423},{"timeStamp":469425,"x":575,"y":423},{"timeStamp":469444,"x":575,"y":423},{"timeStamp":469462,"x":575,"y":423},{"timeStamp":469481,"x":575,"y":423},{"timeStamp":469498,"x":575,"y":423},{"timeStamp":469516,"x":575,"y":423},{"timeStamp":469535,"x":575,"y":423},{"timeStamp":469554,"x":575,"y":423},{"timeStamp":469573,"x":575,"y":423},{"timeStamp":469591.0000000001,"x":575,"y":423},{"timeStamp":469610.0000000001,"x":575,"y":423},{"timeStamp":469627,"x":575,"y":423},{"timeStamp":469645,"x":575,"y":423},{"timeStamp":469664,"x":575,"y":423},{"timeStamp":469681,"x":575,"y":423},{"timeStamp":469697,"x":575,"y":423},{"timeStamp":469716.0000000001,"x":575,"y":423},{"timeStamp":469735.0000000001,"x":575,"y":423},{"timeStamp":469751,"x":575,"y":423},{"timeStamp":469769.0000000001,"x":575,"y":423},{"timeStamp":469786,"x":575,"y":423},{"timeStamp":469805,"x":575,"y":423},{"timeStamp":469821,"x":575,"y":423},{"timeStamp":469839,"x":575,"y":423},{"timeStamp":469856,"x":575,"y":423},{"timeStamp":469877,"x":575,"y":423},{"timeStamp":469896,"x":575,"y":423},{"timeStamp":469915,"x":575,"y":423},{"timeStamp":469934,"x":575,"y":423},{"timeStamp":469951,"x":575,"y":423},{"timeStamp":469970,"x":575,"y":423},{"timeStamp":469988,"x":575,"y":423},{"timeStamp":470007,"x":575,"y":423},{"timeStamp":470027,"x":575,"y":423},{"timeStamp":470046,"x":575,"y":423},{"timeStamp":470063,"x":575,"y":423},{"timeStamp":470081,"x":575,"y":423},{"timeStamp":470101,"x":575,"y":423},{"timeStamp":470117,"x":575,"y":423},{"timeStamp":470134.0000000001,"x":575,"y":423},{"timeStamp":470150,"x":575,"y":423},{"timeStamp":470169,"x":575,"y":423},{"timeStamp":470188,"x":575,"y":423},{"timeStamp":470207,"x":575,"y":423},{"timeStamp":470225,"x":575,"y":423},{"timeStamp":470244,"x":575,"y":423},{"timeStamp":470262,"x":575,"y":423},{"timeStamp":470280,"x":575,"y":423},{"timeStamp":470299,"x":575,"y":423}],"xPos":212,"yPos":424,"pointNumber":29},{"gazeData":[{"timeStamp":471819,"x":575,"y":423},{"timeStamp":471890,"x":575,"y":423},{"timeStamp":471920,"x":575,"y":423},{"timeStamp":471948,"x":575,"y":423},{"timeStamp":471974,"x":575,"y":423},{"timeStamp":471998,"x":575,"y":423},{"timeStamp":472019.0000000001,"x":575,"y":423},{"timeStamp":472038.0000000001,"x":575,"y":423},{"timeStamp":472055,"x":575,"y":423},{"timeStamp":472075,"x":575,"y":423},{"timeStamp":472093,"x":575,"y":423},{"timeStamp":472111,"x":575,"y":423},{"timeStamp":472130,"x":575,"y":423},{"timeStamp":472147,"x":575,"y":423},{"timeStamp":472166,"x":575,"y":423},{"timeStamp":472183,"x":575,"y":423},{"timeStamp":472202,"x":575,"y":423},{"timeStamp":472220,"x":575,"y":423},{"timeStamp":472238,"x":575,"y":423},{"timeStamp":472255,"x":575,"y":423},{"timeStamp":472270,"x":575,"y":423},{"timeStamp":472287,"x":575,"y":423},{"timeStamp":472306,"x":575,"y":423},{"timeStamp":472323,"x":575,"y":423},{"timeStamp":472341.0000000001,"x":575,"y":423},{"timeStamp":472360.0000000001,"x":575,"y":423},{"timeStamp":472379,"x":575,"y":423},{"timeStamp":472398,"x":575,"y":423},{"timeStamp":472415,"x":575,"y":423},{"timeStamp":472433,"x":575,"y":423},{"timeStamp":472449,"x":575,"y":423},{"timeStamp":472466.0000000001,"x":575,"y":423},{"timeStamp":472485.0000000001,"x":575,"y":423},{"timeStamp":472505,"x":575,"y":423},{"timeStamp":472521,"x":575,"y":423},{"timeStamp":472539,"x":575,"y":423},{"timeStamp":472555,"x":575,"y":423},{"timeStamp":472572,"x":575,"y":423},{"timeStamp":472589,"x":575,"y":423},{"timeStamp":472608,"x":575,"y":423},{"timeStamp":472625,"x":575,"y":423},{"timeStamp":472645,"x":575,"y":423},{"timeStamp":472664,"x":575,"y":423},{"timeStamp":472682,"x":575,"y":423},{"timeStamp":472700,"x":575,"y":423},{"timeStamp":472717,"x":575,"y":423},{"timeStamp":472736,"x":575,"y":423},{"timeStamp":472754,"x":575,"y":423},{"timeStamp":472773,"x":575,"y":423},{"timeStamp":472790,"x":575,"y":423},{"timeStamp":472811,"x":575,"y":423},{"timeStamp":472828,"x":575,"y":423},{"timeStamp":472847,"x":575,"y":423},{"timeStamp":472863,"x":575,"y":423},{"timeStamp":472881,"x":575,"y":423},{"timeStamp":472899,"x":575,"y":423},{"timeStamp":472921,"x":575,"y":423},{"timeStamp":472938,"x":575,"y":423},{"timeStamp":472958,"x":575,"y":423},{"timeStamp":472976,"x":575,"y":423},{"timeStamp":472993,"x":575,"y":423},{"timeStamp":473012,"x":575,"y":423},{"timeStamp":473029,"x":575,"y":423},{"timeStamp":473047,"x":575,"y":423},{"timeStamp":473064,"x":575,"y":423},{"timeStamp":473081,"x":575,"y":423},{"timeStamp":473100,"x":575,"y":423},{"timeStamp":473118,"x":575,"y":423},{"timeStamp":473135,"x":575,"y":423},{"timeStamp":473151,"x":575,"y":423},{"timeStamp":473170,"x":575,"y":423},{"timeStamp":473187.0000000001,"x":575,"y":423}],"xPos":576,"yPos":424,"pointNumber":30},{"gazeData":[{"timeStamp":474709,"x":575,"y":423},{"timeStamp":474773,"x":575,"y":423},{"timeStamp":474803,"x":575,"y":423},{"timeStamp":474830,"x":575,"y":423},{"timeStamp":474854,"x":575,"y":423},{"timeStamp":474876,"x":575,"y":423},{"timeStamp":474900,"x":575,"y":423},{"timeStamp":474921,"x":575,"y":423},{"timeStamp":474940,"x":575,"y":423},{"timeStamp":474957,"x":575,"y":423},{"timeStamp":474974,"x":575,"y":423},{"timeStamp":474991,"x":575,"y":423},{"timeStamp":475010,"x":575,"y":423},{"timeStamp":475029,"x":575,"y":423},{"timeStamp":475047,"x":575,"y":423},{"timeStamp":475068,"x":575,"y":423},{"timeStamp":475085,"x":575,"y":423},{"timeStamp":475104,"x":575,"y":423},{"timeStamp":475121,"x":575,"y":423},{"timeStamp":475140,"x":575,"y":423},{"timeStamp":475157,"x":575,"y":423},{"timeStamp":475176,"x":575,"y":423},{"timeStamp":475195,"x":575,"y":423},{"timeStamp":475214,"x":575,"y":423},{"timeStamp":475233,"x":575,"y":423},{"timeStamp":475249,"x":575,"y":423},{"timeStamp":475265,"x":575,"y":423},{"timeStamp":475282,"x":575,"y":423},{"timeStamp":475299,"x":575,"y":423},{"timeStamp":475316,"x":575,"y":423},{"timeStamp":475332,"x":575,"y":423},{"timeStamp":475349,"x":575,"y":423},{"timeStamp":475370,"x":575,"y":423},{"timeStamp":475387,"x":575,"y":423},{"timeStamp":475406,"x":575,"y":423},{"timeStamp":475424,"x":575,"y":423},{"timeStamp":475443,"x":575,"y":423},{"timeStamp":475462,"x":575,"y":423},{"timeStamp":475480,"x":575,"y":423},{"timeStamp":475496,"x":575,"y":423},{"timeStamp":475514.0000000001,"x":575,"y":423},{"timeStamp":475532,"x":575,"y":423},{"timeStamp":475549,"x":575,"y":423},{"timeStamp":475567.0000000001,"x":575,"y":423},{"timeStamp":475584,"x":575,"y":423},{"timeStamp":475603,"x":575,"y":423},{"timeStamp":475621,"x":575,"y":423},{"timeStamp":475641,"x":575,"y":423},{"timeStamp":475660,"x":575,"y":423},{"timeStamp":475678,"x":575,"y":423},{"timeStamp":475697,"x":575,"y":423},{"timeStamp":475714,"x":575,"y":423},{"timeStamp":475733,"x":575,"y":423},{"timeStamp":475751,"x":575,"y":423},{"timeStamp":475770,"x":575,"y":423},{"timeStamp":475787,"x":575,"y":423},{"timeStamp":475806,"x":575,"y":423},{"timeStamp":475826,"x":575,"y":423},{"timeStamp":475845,"x":575,"y":423},{"timeStamp":475861,"x":575,"y":423},{"timeStamp":475878,"x":575,"y":423},{"timeStamp":475894.0000000001,"x":575,"y":423},{"timeStamp":475912,"x":575,"y":423},{"timeStamp":475929,"x":575,"y":423},{"timeStamp":475949,"x":575,"y":423},{"timeStamp":475967,"x":575,"y":423}],"xPos":940,"yPos":818,"pointNumber":31},{"gazeData":[{"timeStamp":477486,"x":575,"y":423},{"timeStamp":477540,"x":575,"y":423},{"timeStamp":477569,"x":575,"y":423},{"timeStamp":477593,"x":575,"y":423},{"timeStamp":477617,"x":575,"y":423},{"timeStamp":477641,"x":575,"y":423},{"timeStamp":477659,"x":575,"y":423},{"timeStamp":477679,"x":575,"y":423},{"timeStamp":477697,"x":575,"y":423},{"timeStamp":477717,"x":575,"y":423},{"timeStamp":477736,"x":575,"y":423},{"timeStamp":477753,"x":575,"y":423},{"timeStamp":477772,"x":575,"y":423},{"timeStamp":477789,"x":575,"y":423},{"timeStamp":477808,"x":575,"y":423},{"timeStamp":477827,"x":575,"y":423},{"timeStamp":477845,"x":575,"y":423},{"timeStamp":477863,"x":575,"y":423},{"timeStamp":477883,"x":575,"y":423},{"timeStamp":477902,"x":575,"y":423},{"timeStamp":477919,"x":575,"y":423},{"timeStamp":477938,"x":575,"y":423},{"timeStamp":477955,"x":575,"y":423},{"timeStamp":477974,"x":575,"y":423},{"timeStamp":477993,"x":575,"y":423},{"timeStamp":478012,"x":575,"y":423},{"timeStamp":478031,"x":575,"y":423},{"timeStamp":478048,"x":575,"y":423},{"timeStamp":478066,"x":575,"y":423},{"timeStamp":478083,"x":575,"y":423},{"timeStamp":478102,"x":575,"y":423},{"timeStamp":478119,"x":575,"y":423},{"timeStamp":478138,"x":575,"y":423},{"timeStamp":478155,"x":575,"y":423},{"timeStamp":478174,"x":575,"y":423},{"timeStamp":478193,"x":575,"y":423},{"timeStamp":478211.0000000001,"x":575,"y":423},{"timeStamp":478230,"x":575,"y":423},{"timeStamp":478248,"x":575,"y":423},{"timeStamp":478267,"x":575,"y":423},{"timeStamp":478285,"x":575,"y":423},{"timeStamp":478303,"x":575,"y":423},{"timeStamp":478319,"x":575,"y":423},{"timeStamp":478337,"x":575,"y":423},{"timeStamp":478354,"x":575,"y":423},{"timeStamp":478373,"x":575,"y":423},{"timeStamp":478390,"x":575,"y":423},{"timeStamp":478408,"x":575,"y":423},{"timeStamp":478428,"x":575,"y":423},{"timeStamp":478446,"x":575,"y":423},{"timeStamp":478465,"x":575,"y":423},{"timeStamp":478482,"x":575,"y":423},{"timeStamp":478503,"x":575,"y":423},{"timeStamp":478521,"x":575,"y":423},{"timeStamp":478540,"x":575,"y":423},{"timeStamp":478557,"x":575,"y":423},{"timeStamp":478576,"x":575,"y":423},{"timeStamp":478596,"x":575,"y":423},{"timeStamp":478614,"x":575,"y":423},{"timeStamp":478631,"x":575,"y":423},{"timeStamp":478649,"x":575,"y":423},{"timeStamp":478668.0000000001,"x":575,"y":423},{"timeStamp":478685,"x":575,"y":423},{"timeStamp":478702,"x":575,"y":423},{"timeStamp":478719,"x":575,"y":423},{"timeStamp":478738,"x":575,"y":423},{"timeStamp":478756,"x":575,"y":423},{"timeStamp":478774,"x":575,"y":423},{"timeStamp":478792,"x":575,"y":423},{"timeStamp":478812.0000000001,"x":575,"y":423},{"timeStamp":478830,"x":575,"y":423},{"timeStamp":478848,"x":575,"y":423}],"xPos":212,"yPos":30,"pointNumber":32}],"dimensions":{"x":0,"y":0,"h":848,"w":1152},"time":"2021-09-10 20:42:02"}],"answers":[],"Technical":{"Camera":{"cameraLabel":"FaceTime HD Camera","frameRate":30,"height":480,"width":640},"Agent":"Mozilla\/5.0 (Macintosh; Intel Mac OS X 10_15_7) AppleWebKit\/605.1.15 (KHTML, like Gecko) Version\/14.1.1 Safari\/605.1.15","Language":"en-gb"}}